Workbook

Sheet DASHBOARD
C2: SCENARIO | D2: Base | H2: Pessmistic | I2: Base | J2: Optmistic
C3: Choose Base/Pessimistic/Optimistic Scenarios, the Financial model Updates automatially

Sheet FS
B2: Years (As on March) | C2: 2017 | D2: =C2+1 -> 2018 | E2: =D2+1 -> 2019 | F2: =E2+1 -> 2020 | G2: =F2+1 -> 2021 | H2: =G2+1 -> 2022 | I2: =H2+1 -> 2023 | J2: =I2+1 -> 2024 | K2: =J2+1 -> 2025 | ... Q2: =P2+1 -> 2031 | S2: CAGR
B3: Revenue | C3: ='Forecast Drivers'!C7 -> 59289 | D3: ='Forecast Drivers'!D7 -> 61941 | E3: ='Forecast Drivers'!E7 -> 73107 | F3: ='Forecast Drivers'!F7 -> 79047 | G3: ='Forecast Drivers'!G7 -> 85912 | H3: ='Forecast Drivers'!H7 -> 103940 | I3: ='Forecast Drivers'!I7 -> 124014 | J3: ='Forecast Drivers'!J7 -> 128933 | ... Q3: ='Forecast Drivers'!Q7 -> 217072.46 | S3: =_xlfn.RRI(5,L3,Q3) -> 0.078423314
B5: Clients | C5: ='Forecast Drivers'!C9 -> 1162 | D5: ='Forecast Drivers'!D9 -> 1204 | E5: ='Forecast Drivers'!E9 -> 1279 | F5: ='Forecast Drivers'!F9 -> 1411 | G5: ='Forecast Drivers'!G9 -> 1626 | H5: ='Forecast Drivers'!H9 -> 1741 | I5: ='Forecast Drivers'!I9 -> 1872 | J5: ='Forecast Drivers'!J9 -> 1882 | ... Q5: ='Forecast Drivers'!Q9 -> 2291.9487 | S5: =_xlfn.RRI(5,L5,Q5) -> 0.031260703
B7: EBITDA | C7: ='Forecast Drivers'!C7-'Forecast Drivers'!C32-'Forecast Drivers'!C47 -> 17207 | D7: ='Forecast Drivers'!D7-'Forecast Drivers'!D32-'Forecast Drivers'!D47 -> 17297 | E7: ='Forecast Drivers'!E7-'Forecast Drivers'!E32-'Forecast Drivers'!E47 -> 18674 | F7: ='Forecast Drivers'!F7-'Forecast Drivers'!F32-'Forecast Drivers'!F47 -> 20035 | G7: ='Forecast Drivers'!G7-'Forecast Drivers'!G32-'Forecast Drivers'!G47 -> 24457 | H7: ='Forecast Drivers'!H7-'Forecast Drivers'!H32-'Forecast Drivers'!H47 -> 27828 | I7: ='Forecast Drivers'!I7-'Forecast Drivers'!I32-'Forecast Drivers'!I47 -> 30694 | J7: ='Forecast Drivers'!J7-'Forecast Drivers'!J32-'Forecast Drivers'!J47 -> 31757 | ... Q7: ='Forecast Drivers'!Q7-'Forecast Drivers'!Q32-'Forecast Drivers'!Q47 -> 58479.607 | S7: =_xlfn.RRI(5,L7,Q7) -> 0.10181588
B11: Years (As on March) | C11: 2017 | D11: =C11+1 -> 2018 | E11: =D11+1 -> 2019 | F11: =E11+1 -> 2020 | G11: =F11+1 -> 2021 | H11: =G11+1 -> 2022 | I11: =H11+1 -> 2023 | J11: =I11+1 -> 2024 | K11: =J11+1 -> 2025 | ... Q11: =P11+1 -> 2031
B12: Revenue | C12: =C3 -> 59289 | D12: =D3 -> 61941 | E12: =E3 -> 73107 | F12: =F3 -> 79047 | G12: =G3 -> 85912 | H12: =H3 -> 103940 | I12: =I3 -> 124014 | J12: =J3 -> 128933 | ... Q12: =Q3 -> 217072.46
B13: EBITDA | C13: =C7 -> 17207 | D13: =D7 -> 17297 | E13: =E7 -> 18674 | F13: =F7 -> 20035 | G13: =G7 -> 24457 | H13: =H7 -> 27828 | I13: =I7 -> 30694 | J13: =J7 -> 31757 | ... Q13: =Q7 -> 58479.607
B16: Years (As on March) | C16: 2017 | D16: =C16+1 -> 2018 | E16: =D16+1 -> 2019 | F16: =E16+1 -> 2020 | G16: =F16+1 -> 2021 | H16: =G16+1 -> 2022 | I16: =H16+1 -> 2023 | J16: =I16+1 -> 2024 | K16: =J16+1 -> 2025 | ... Q16: =P16+1 -> 2031
B17: Clients | C17: =C5 -> 1162 | D17: =D5 -> 1204 | E17: =E5 -> 1279 | F17: =F5 -> 1411 | G17: =G5 -> 1626 | H17: =H5 -> 1741 | I17: =I5 -> 1872 | J17: =J5 -> 1882 | ... Q17: =Q5 -> 2291.9487
B19: Years (As on March) | C19: 2017 | D19: =C19+1 -> 2018 | E19: =D19+1 -> 2019 | F19: =E19+1 -> 2020 | G19: =F19+1 -> 2021 | H19: =G19+1 -> 2022 | I19: =H19+1 -> 2023 | J19: =I19+1 -> 2024 | K19: =J19+1 -> 2025 | ... Q19: =P19+1 -> 2031
B20: Large clients ( >50 M $) | C20: ='Forecast Drivers'!C16 -> 75 | D20: ='Forecast Drivers'!D16 -> 77 | E20: ='Forecast Drivers'!E16 -> 85 | F20: ='Forecast Drivers'!F16 -> 28 | G20: ='Forecast Drivers'!G16 -> 32 | H20: ='Forecast Drivers'!H16 -> 38 | I20: ='Forecast Drivers'!I16 -> 115 | J20: ='Forecast Drivers'!J16 -> 123 | ... Q20: ='Forecast Drivers'!Q16 -> 169.5649
B22: Years (As on March) | C22: 2017 | D22: =C22+1 -> 2018 | E22: =D22+1 -> 2019 | F22: =E22+1 -> 2020 | G22: =F22+1 -> 2021 | H22: =G22+1 -> 2022 | I22: =H22+1 -> 2023 | J22: =I22+1 -> 2024 | K22: =J22+1 -> 2025 | ... Q22: =P22+1 -> 2031
B23: Other clients | C23: ='Forecast Drivers'!C23 -> 1087 | D23: ='Forecast Drivers'!D23 -> 1127 | E23: ='Forecast Drivers'!E23 -> 1194 | F23: ='Forecast Drivers'!F23 -> 1383 | G23: ='Forecast Drivers'!G23 -> 1594 | H23: ='Forecast Drivers'!H23 -> 1703 | I23: ='Forecast Drivers'!I23 -> 1757 | J23: ='Forecast Drivers'!J23 -> 1759 | ... Q23: ='Forecast Drivers'!Q23 -> 2356.7421
B24: Large clients ( >50 M $) | C24: =C20 -> 75 | D24: =D20 -> 77 | E24: =E20 -> 85 | F24: =F20 -> 28 | G24: =G20 -> 32 | H24: =H20 -> 38 | I24: =I20 -> 115 | J24: =J20 -> 123 | ... Q24: =Q20 -> 169.5649
B28: Particulars | C28: Infosys | D28: TCS | E28: HCL | F28: Wipro
B29: EV/EBITDA | C29: ='EV-EBITDA'!C14 -> 12.752719 | D29: ='EV-EBITDA'!D14 -> 11.68647 | E29: ='EV-EBITDA'!E14 -> 20.703031 | F29: ='EV-EBITDA'!F14 -> 10.599802
B31: Years (As on March) | C31: 2017 | D31: =C31+1 -> 2018 | E31: =D31+1 -> 2019 | F31: =E31+1 -> 2020 | G31: =F31+1 -> 2021 | H31: =G31+1 -> 2022 | I31: =H31+1 -> 2023 | J31: =I31+1 -> 2024 | K31: =J31+1 -> 2025 | ... Q31: =P31+1 -> 2031
B32: Revenue per employee | C32: =C36/$C$36*100 -> 100 | D32: =D36/$C$36*100 -> 102.55714 | E32: =E36/$C$36*100 -> 108.30175 | F32: =F36/$C$36*100 -> 110.21744 | G32: =G36/$C$36*100 -> 111.83118 | H32: =H36/$C$36*100 -> 111.86079 | I32: =I36/$C$36*100 -> 122.1029 | J32: =J36/$C$36*100 -> 137.3478 | ... Q32: =Q36/$C$36*100 -> 204.45898
B33: Employee cost per employee | C33: =C37/$C$37*100 -> 100 | D33: =D37/$C$37*100 -> 103.01215 | E33: =E37/$C$37*100 -> 108.68777 | F33: =F37/$C$37*100 -> 113.35277 | G33: =G37/$C$37*100 -> 112.6613 | H33: =H37/$C$37*100 -> 106.52389 | I33: =I37/$C$37*100 -> 118.39709 | J33: =J37/$C$37*100 -> 132.94645 | ... Q33: =Q37/$C$37*100 -> 177.45842
B36: Revenue per employee | C36: ='Forecast Drivers'!C7/'Forecast Drivers'!C36 -> 0.29590645 | D36: ='Forecast Drivers'!D7/'Forecast Drivers'!D36 -> 0.30347318 | E36: ='Forecast Drivers'!E7/'Forecast Drivers'!E36 -> 0.32047185 | F36: ='Forecast Drivers'!F7/'Forecast Drivers'!F36 -> 0.3261405 | G36: ='Forecast Drivers'!G7/'Forecast Drivers'!G36 -> 0.33091569 | H36: ='Forecast Drivers'!H7/'Forecast Drivers'!H36 -> 0.3310033 | I36: ='Forecast Drivers'!I7/'Forecast Drivers'!I36 -> 0.36131036 | J36: ='Forecast Drivers'!J7/'Forecast Drivers'!J36 -> 0.40642101 | ... Q36: ='Forecast Drivers'!Q7/'Forecast Drivers'!Q36 -> 0.60500731
B37: Employee cost per employee | C37: ='Forecast Drivers'!C39 -> 0.15448384 | D37: ='Forecast Drivers'!D39 -> 0.15913712 | E37: ='Forecast Drivers'!E39 -> 0.16790503 | F37: ='Forecast Drivers'!F39 -> 0.17511171 | G37: ='Forecast Drivers'!G39 -> 0.1740435 | H37: ='Forecast Drivers'!H39 -> 0.1645622 | I37: ='Forecast Drivers'!I39 -> 0.18290437 | J37: ='Forecast Drivers'!J39 -> 0.20538078 | ... Q37: ='Forecast Drivers'!Q39 -> 0.27414459

Sheet Financials>>

Sheet Historical FS
L1: in CR
B2: ='DATA Sheet'!B1&" Historical FS" -> INFOSYS LTD Historical FS
B3: Years | C3: FY17 | D3: FY18 | E3: FY19 | F3: FY20 | G3: FY21 | H3: FY22 | I3: FY23 | J3: FY24 | K3: FY25 | L3: FY26
A4: # | B4: Income Statement
B5: Sales | C5: ='DATA Sheet'!B17 -> 59289 | D5: ='DATA Sheet'!C17 -> 61941 | E5: ='DATA Sheet'!D17 -> 73107 | F5: ='DATA Sheet'!E17 -> 79047 | G5: ='DATA Sheet'!F17 -> 85912 | H5: ='DATA Sheet'!G17 -> 103940 | I5: ='DATA Sheet'!H17 -> 124014 | J5: ='DATA Sheet'!I17 -> 128933 | ... L5: ='DATA Sheet'!K17 -> 148819
B6: Sales Growth | D6: =D5/C5-1 -> 0.044730051 | E6: =E5/D5-1 -> 0.18026832 | F6: =F5/E5-1 -> 0.081250769 | G6: =G5/F5-1 -> 0.086847066 | H6: =H5/G5-1 -> 0.20984263 | I6: =I5/H5-1 -> 0.19313065 | J6: =J5/I5-1 -> 0.039664877 | K6: =K5/J5-1 -> 0.059402946 | L6: =L5/K5-1 -> 0.089514759
B8: COGS | C8: =SUM('DATA Sheet'!B18:B22) -> 38281 | D8: =SUM('DATA Sheet'!C18:C22) -> 40331 | E8: =SUM('DATA Sheet'!D18:D22) -> 48850 | F8: =SUM('DATA Sheet'!E18:E22) -> 53988 | G8: =SUM('DATA Sheet'!F18:F22) -> 57966 | H8: =SUM('DATA Sheet'!G18:G22) -> 71916 | I8: =SUM('DATA Sheet'!H18:H22) -> 88211 | J8: =SUM('DATA Sheet'!I18:I22) -> 91832 | ... L8: =SUM('DATA Sheet'!K18:K22) -> 106285
B9: % of sales | C9: =C8/C5 -> 0.64566783 | D9: =D8/D5 -> 0.65111961 | E9: =E8/E5 -> 0.66819867 | F9: =F8/F5 -> 0.68298607 | G9: =G8/G5 -> 0.67471366 | H9: =H8/H5 -> 0.69189917 | I9: =I8/I5 -> 0.71129872 | J9: =J8/J5 -> 0.7122459 | ... L9: =L8/L5 -> 0.71418972
B11: Gross Profit | C11: =C5-C8 -> 21008 | D11: =D5-D8 -> 21610 | E11: =E5-E8 -> 24257 | F11: =F5-F8 -> 25059 | G11: =G5-G8 -> 27946 | H11: =H5-H8 -> 32024 | I11: =I5-I8 -> 35803 | J11: =J5-J8 -> 37101 | ... L11: =L5-L8 -> 42534
B12: Gross margin | C12: =C11/C5 -> 0.35433217 | D12: =D11/D5 -> 0.34888039 | E12: =E11/E5 -> 0.33180133 | F12: =F11/F5 -> 0.31701393 | G12: =G11/G5 -> 0.32528634 | H12: =H11/H5 -> 0.30810083 | I12: =I11/I5 -> 0.28870128 | J12: =J11/J5 -> 0.2877541 | ... L12: =L11/L5 -> 0.28581028
B15: SG&A | C15: ='DATA Sheet'!B23+'DATA Sheet'!B24 -> 3801 | D15: ='DATA Sheet'!C23+'DATA Sheet'!C24 -> 4313 | E15: ='DATA Sheet'!D23+'DATA Sheet'!D24 -> 5583 | F15: ='DATA Sheet'!E23+'DATA Sheet'!E24 -> 5024 | G15: ='DATA Sheet'!F23+'DATA Sheet'!F24 -> 3489 | H15: ='DATA Sheet'!G23+'DATA Sheet'!G24 -> 4196 | I15: ='DATA Sheet'!H23+'DATA Sheet'!H24 -> 5109 | J15: ='DATA Sheet'!I23+'DATA Sheet'!I24 -> 5344 | ... L15: ='DATA Sheet'!K23+'DATA Sheet'!K24 -> 6521
B16: % of sales | C16: =C15/C5 -> 0.0641097 | D16: =D15/D5 -> 0.069630778 | E16: =E15/E5 -> 0.076367516 | F16: =F15/F5 -> 0.063557124 | G16: =G15/G5 -> 0.040611323 | H16: =H15/H5 -> 0.040369444 | I16: =I15/I5 -> 0.041196962 | J16: =J15/J5 -> 0.041447884 | ... L16: =L15/L5 -> 0.04381833
B18: EBITDA | C18: =C11-C15 -> 17207 | D18: =D11-D15 -> 17297 | E18: =E11-E15 -> 18674 | F18: =F11-F15 -> 20035 | G18: =G11-G15 -> 24457 | H18: =H11-H15 -> 27828 | I18: =I11-I15 -> 30694 | J18: =J11-J15 -> 31757 | ... L18: =L11-L15 -> 36013
B19: % of sales | C19: =C18/C5 -> 0.29022247 | D19: =D18/D5 -> 0.27924961 | E19: =E18/E5 -> 0.25543382 | F19: =F18/F5 -> 0.2534568 | G19: =G18/G5 -> 0.28467502 | H19: =H18/H5 -> 0.26773138 | I19: =I18/I5 -> 0.24750431 | J19: =J18/J5 -> 0.24630622 | ... L19: =L18/L5 -> 0.24199195
B22: Interest | C22: ='DATA Sheet'!B27 -> 0 | D22: ='DATA Sheet'!C27 -> 0 | E22: ='DATA Sheet'!D27 -> 0 | F22: ='DATA Sheet'!E27 -> 114 | G22: ='DATA Sheet'!F27 -> 126 | H22: ='DATA Sheet'!G27 -> 128 | I22: ='DATA Sheet'!H27 -> 157 | J22: ='DATA Sheet'!I27 -> 277 | ... L22: ='DATA Sheet'!K27 -> 207
B25: Depreciation | C25: ='DATA Sheet'!B26 -> 1331 | D25: ='DATA Sheet'!C26 -> 1408 | E25: ='DATA Sheet'!D26 -> 1599 | F25: ='DATA Sheet'!E26 -> 2144 | G25: ='DATA Sheet'!F26 -> 2321 | H25: ='DATA Sheet'!G26 -> 2429 | I25: ='DATA Sheet'!H26 -> 2753 | J25: ='DATA Sheet'!I26 -> 2944 | ... L25: ='DATA Sheet'!K26 -> 2394
B28: Other Income | C28: ='DATA Sheet'!B25 -> 3062 | D28: ='DATA Sheet'!C25 -> 4019 | E28: ='DATA Sheet'!D25 -> 2852 | F28: ='DATA Sheet'!E25 -> 2700 | G28: ='DATA Sheet'!F25 -> 2467 | H28: ='DATA Sheet'!G25 -> 3224 | I28: ='DATA Sheet'!H25 -> 3859 | J28: ='DATA Sheet'!I25 -> 7417 | ... L28: ='DATA Sheet'!K25 -> 5345
B31: PBT | C31: =C18+C28-C25-C22 -> 18938 | D31: =D18+D28-D25-D22 -> 19908 | E31: =E18+E28-E25-E22 -> 19927 | F31: =F18+F28-F25-F22 -> 20477 | G31: =G18+G28-G25-G22 -> 24477 | H31: =H18+H28-H25-H22 -> 28495 | I31: =I18+I28-I25-I22 -> 31643 | J31: =J18+J28-J25-J22 -> 35953 | ... L31: =L18+L28-L25-L22 -> 38757
B32: % of sales | C32: =C31/C5 -> 0.31941844 | D32: =D31/D5 -> 0.32140263 | E32: =E31/E5 -> 0.27257308 | F32: =F31/F5 -> 0.25904841 | G32: =G31/G5 -> 0.28490781 | H32: =H31/H5 -> 0.27414855 | I32: =I31/I5 -> 0.25515668 | J32: =J31/J5 -> 0.27885026 | ... L32: =L31/L5 -> 0.26043046
B34: Tax | C34: ='DATA Sheet'!B29 -> 5120 | D34: ='DATA Sheet'!C29 -> 3753 | E34: ='DATA Sheet'!D29 -> 5225 | F34: ='DATA Sheet'!E29 -> 4934 | G34: ='DATA Sheet'!F29 -> 6429 | H34: ='DATA Sheet'!G29 -> 7260 | I34: ='DATA Sheet'!H29 -> 8375 | J34: ='DATA Sheet'!I29 -> 8719 | ... L34: ='DATA Sheet'!K29 -> 9546
B35: Effective rate | C35: =C34/C31 -> 0.2703559 | D35: =D34/D31 -> 0.18851718 | E35: =E34/E31 -> 0.26220706 | F35: =F34/F31 -> 0.24095326 | G35: =G34/G31 -> 0.26265474 | H35: =H34/H31 -> 0.25478154 | I35: =I34/I31 -> 0.26467149 | J35: =J34/J31 -> 0.24251106 | ... L35: =L34/L31 -> 0.24630389
B37: Net profit | C37: =C31-C34 -> 13818 | D37: =D31-D34 -> 16155 | E37: =E31-E34 -> 14702 | F37: =F31-F34 -> 15543 | G37: =G31-G34 -> 18048 | H37: =H31-H34 -> 21235 | I37: =I31-I34 -> 23268 | J37: =J31-J34 -> 27234 | ... L37: =L31-L34 -> 29211
B39: Dividend | C39: ='DATA Sheet'!B31 -> 5912.2 | D39: ='DATA Sheet'!C31 -> 9500.4 | E39: ='DATA Sheet'!D31 -> 9365.4 | F39: ='DATA Sheet'!E31 -> 7451.5 | G39: ='DATA Sheet'!F31 -> 11502 | H39: ='DATA Sheet'!G31 -> 13038.6 | I39: ='DATA Sheet'!H31 -> 14103.2 | J39: ='DATA Sheet'!I31 -> 19090 | ... L39: ='DATA Sheet'!K31 -> 19459.2
B40: Dividend ratio | C40: =C39/C37 -> 0.42786221 | D40: =D39/D37 -> 0.58807799 | E40: =E39/E37 -> 0.63701537 | F40: =F39/F37 -> 0.47941195 | G40: =G39/G37 -> 0.63730053 | H40: =H39/H37 -> 0.6140146 | I40: =I39/I37 -> 0.60611999 | J40: =J39/J37 -> 0.70096203 | ... L40: =L39/L37 -> 0.66616001
B41: Retention Ratio | C41: =1-C40 -> 0.57213779 | D41: =1-D40 -> 0.41192201 | E41: =1-E40 -> 0.36298463 | F41: =1-F40 -> 0.52058805 | G41: =1-G40 -> 0.36269947 | H41: =1-H40 -> 0.3859854 | I41: =1-I40 -> 0.39388001 | J41: =1-J40 -> 0.29903797 | ... L41: =1-L40 -> 0.33383999
A43: # | B43: Balance Sheet
B45: Equity Share Capital | C45: ='DATA Sheet'!B57 -> 1148 | D45: ='DATA Sheet'!C57 -> 1092 | E45: ='DATA Sheet'!D57 -> 2178 | F45: ='DATA Sheet'!E57 -> 2129 | G45: ='DATA Sheet'!F57 -> 2130 | H45: ='DATA Sheet'!G57 -> 2103 | I45: ='DATA Sheet'!H57 -> 2074 | J45: ='DATA Sheet'!I57 -> 2075 | ... L45: ='DATA Sheet'!K57 -> 2027
B46: Reserves | C46: ='DATA Sheet'!B58 -> 66869 | D46: ='DATA Sheet'!C58 -> 62410 | E46: ='DATA Sheet'!D58 -> 60533 | F46: ='DATA Sheet'!E58 -> 60105 | G46: ='DATA Sheet'!F58 -> 69401 | H46: ='DATA Sheet'!G58 -> 67203 | I46: ='DATA Sheet'!H58 -> 65671 | J46: ='DATA Sheet'!I58 -> 79101 | ... L46: ='DATA Sheet'!K58 -> 78847
B47: Borrowings | C47: ='DATA Sheet'!B59 -> 0 | D47: ='DATA Sheet'!C59 -> 0 | E47: ='DATA Sheet'!D59 -> 0 | F47: ='DATA Sheet'!E59 -> 3165 | G47: ='DATA Sheet'!F59 -> 3854 | H47: ='DATA Sheet'!G59 -> 3786 | I47: ='DATA Sheet'!H59 -> 4266 | J47: ='DATA Sheet'!I59 -> 3766 | ... L47: ='DATA Sheet'!K59 -> 3749
B48: Other Liabilities | C48: ='DATA Sheet'!B60 -> 11868 | D48: ='DATA Sheet'!C60 -> 11870 | E48: ='DATA Sheet'!D60 -> 15678 | F48: ='DATA Sheet'!E60 -> 15086 | G48: ='DATA Sheet'!F60 -> 18043 | H48: ='DATA Sheet'!G60 -> 25454 | I48: ='DATA Sheet'!H60 -> 28547 | J48: ='DATA Sheet'!I60 -> 30008 | ... L48: ='DATA Sheet'!K60 -> 41078
B50: Total Liablities | C50: =SUM(C45:C48) -> 79885 | D50: =SUM(D45:D48) -> 75372 | E50: =SUM(E45:E48) -> 78389 | F50: =SUM(F45:F48) -> 80485 | G50: =SUM(G45:G48) -> 93428 | H50: =SUM(H45:H48) -> 98546 | I50: =SUM(I45:I48) -> 100558 | J50: =SUM(J45:J48) -> 114950 | ... L50: =SUM(L45:L48) -> 125701
B53: Fixed Assets | C53: ='DATA Sheet'!B62 -> 8605 | D53: ='DATA Sheet'!C62 -> 9157 | E53: ='DATA Sheet'!D62 -> 10497 | F53: ='DATA Sheet'!E62 -> 13974 | G53: ='DATA Sheet'!F62 -> 14599 | H53: ='DATA Sheet'!G62 -> 14938 | I53: ='DATA Sheet'!H62 -> 15431 | J53: ='DATA Sheet'!I62 -> 14327 | ... L53: ='DATA Sheet'!K62 -> 13836
B54: Capital Work in Progress | C54: ='DATA Sheet'!B63 -> 1247 | D54: ='DATA Sheet'!C63 -> 1442 | E54: ='DATA Sheet'!D63 -> 1212 | F54: ='DATA Sheet'!E63 -> 945 | G54: ='DATA Sheet'!F63 -> 906 | H54: ='DATA Sheet'!G63 -> 411 | I54: ='DATA Sheet'!H63 -> 275 | J54: ='DATA Sheet'!I63 -> 277 | ... L54: ='DATA Sheet'!K63 -> 512
B55: Investments | C55: ='DATA Sheet'!B64 -> 24977 | D55: ='DATA Sheet'!C64 -> 17899 | E55: ='DATA Sheet'!D64 -> 18139 | F55: ='DATA Sheet'!E64 -> 17922 | G55: ='DATA Sheet'!F64 -> 24155 | H55: ='DATA Sheet'!G64 -> 28336 | I55: ='DATA Sheet'!H64 -> 28162 | J55: ='DATA Sheet'!I64 -> 34659 | ... L55: ='DATA Sheet'!K64 -> 38075
B57: Total Non Current Assets | C57: =SUM(C53:C55) -> 34829 | D57: =SUM(D53:D55) -> 28498 | E57: =SUM(E53:E55) -> 29848 | F57: =SUM(F53:F55) -> 32841 | G57: =SUM(G53:G55) -> 39660 | H57: =SUM(H53:H55) -> 43685 | I57: =SUM(I53:I55) -> 43868 | J57: =SUM(J53:J55) -> 49263 | ... L57: =SUM(L53:L55) -> 52423
B59: Trade receivables | C59: ='Balance sheet'!E13 -> 10960 | D59: ='Balance sheet'!F13 -> 12151 | E59: ='Balance sheet'!G13 -> 13370 | F59: ='Balance sheet'!H13 -> 15459 | G59: ='Balance sheet'!I13 -> 16394 | H59: ='Balance sheet'!J13 -> 18966 | I59: ='Balance sheet'!K13 -> 20773 | J59: ='Balance sheet'!L13 -> 25152 | ... L59: ='Balance sheet'!N13 -> 30337
B60: Cash Equivalents | C60: ='Balance sheet'!E14 -> 19153 | D60: ='Balance sheet'!F14 -> 16770 | E60: ='Balance sheet'!G14 -> 15551 | F60: ='Balance sheet'!H14 -> 13562 | G60: ='Balance sheet'!I14 -> 17612 | H60: ='Balance sheet'!J14 -> 12270 | I60: ='Balance sheet'!K14 -> 6534 | J60: ='Balance sheet'!L14 -> 8191 | ... L60: ='Balance sheet'!N14 -> 8727
B61: Loans and Advances | C61: ='Balance sheet'!E15 -> 715 | D61: ='Balance sheet'!F15 -> 760 | E61: ='Balance sheet'!G15 -> 1304 | F61: ='Balance sheet'!H15 -> 1069 | G61: ='Balance sheet'!I15 -> 1138 | H61: ='Balance sheet'!J15 -> 1576 | I61: ='Balance sheet'!K15 -> 2124 | J61: ='Balance sheet'!L15 -> 8748 | ... L61: ='Balance sheet'!N15 -> 5571
B62: Other asset items | C62: ='Balance sheet'!E16 -> 14228 | D62: ='Balance sheet'!F16 -> 17193 | E62: ='Balance sheet'!G16 -> 18316 | F62: ='Balance sheet'!H16 -> 17554 | G62: ='Balance sheet'!I16 -> 18624 | H62: ='Balance sheet'!J16 -> 22049 | I62: ='Balance sheet'!K16 -> 27259 | J62: ='Balance sheet'!L16 -> 23596 | ... L62: ='Balance sheet'!N16 -> 28643
B64: Total Current Assets | C64: =SUM(C59:C62) -> 45056 | D64: =SUM(D59:D62) -> 46874 | E64: =SUM(E59:E62) -> 48541 | F64: =SUM(F59:F62) -> 47644 | G64: =SUM(G59:G62) -> 53768 | H64: =SUM(H59:H62) -> 54861 | I64: =SUM(I59:I62) -> 56690 | J64: =SUM(J59:J62) -> 65687 | ... L64: =SUM(L59:L62) -> 73278
B66: Total assets | C66: =C64+C57 -> 79885 | D66: =D64+D57 -> 75372 | E66: =E64+E57 -> 78389 | F66: =F64+F57 -> 80485 | G66: =G64+G57 -> 93428 | H66: =H64+H57 -> 98546 | I66: =I64+I57 -> 100558 | J66: =J64+J57 -> 114950 | ... L66: =L64+L57 -> 125701
B68: Check | C68: =C66=C50 -> TRUE | D68: =D66=D50 -> TRUE | E68: =E66=E50 -> TRUE | F68: =F66=F50 -> TRUE | G68: =G66=G50 -> TRUE | H68: =H66=H50 -> TRUE | I68: =I66=I50 -> TRUE | J68: =J66=J50 -> TRUE | ... L68: =L66=L50 -> TRUE
A71: # | B71: Cashflow Statement
B74: Cash from Operating Activity | C74: ='DATA Sheet'!B82 -> 10478 | D74: ='DATA Sheet'!C82 -> 12475 | E74: ='DATA Sheet'!D82 -> 13989 | F74: ='DATA Sheet'!E82 -> 15572 | G74: ='DATA Sheet'!F82 -> 19902 | H74: ='DATA Sheet'!G82 -> 22096 | I74: ='DATA Sheet'!H82 -> 19169 | J74: ='DATA Sheet'!I82 -> 20787 | ... L74: ='DATA Sheet'!K82 -> 28164
B75: Cash from Investing Activity | C75: ='DATA Sheet'!B83 -> -13533 | D75: ='DATA Sheet'!C83 -> 5678 | E75: ='DATA Sheet'!D83 -> -637 | F75: ='DATA Sheet'!E83 -> -170 | G75: ='DATA Sheet'!F83 -> -6286 | H75: ='DATA Sheet'!G83 -> -3163 | I75: ='DATA Sheet'!H83 -> 952 | J75: ='DATA Sheet'!I83 -> -3305 | ... L75: ='DATA Sheet'!K83 -> 4085
B76: Cash from Financing Activity | C76: ='DATA Sheet'!B84 -> -6968 | D76: ='DATA Sheet'!C84 -> -20536 | E76: ='DATA Sheet'!D84 -> -14571 | F76: ='DATA Sheet'!E84 -> -17391 | G76: ='DATA Sheet'!F84 -> -9566 | H76: ='DATA Sheet'!G84 -> -24275 | I76: ='DATA Sheet'!H84 -> -25857 | J76: ='DATA Sheet'!I84 -> -15825 | ... L76: ='DATA Sheet'!K84 -> -37787
B78: Net Cash Flow | C78: =SUM(C74:C76) -> -10023 | D78: =SUM(D74:D76) -> -2383 | E78: =SUM(E74:E76) -> -1219 | F78: =SUM(F74:F76) -> -1989 | G78: =SUM(G74:G76) -> 4050 | H78: =SUM(H74:H76) -> -5342 | I78: =SUM(I74:I76) -> -5736 | J78: =SUM(J74:J76) -> 1657 | ... L78: =SUM(L74:L76) -> -5538

Sheet Ratio Analysis
B2: ='DATA Sheet'!B1&" Ratio Analysis" -> INFOSYS LTD Ratio Analysis
B3: Years | C3: FY17 | D3: FY18 | E3: FY19 | F3: FY20 | G3: FY21 | H3: FY22 | I3: FY23 | J3: FY24 | K3: FY25 | L3: FY26
A4: #
B5: Sales Growth | D5: ='Historical FS'!D6 -> 0.044730051 | E5: ='Historical FS'!E6 -> 0.18026832 | F5: ='Historical FS'!F6 -> 0.081250769 | G5: ='Historical FS'!G6 -> 0.086847066 | H5: ='Historical FS'!H6 -> 0.20984263 | I5: ='Historical FS'!I6 -> 0.19313065 | J5: ='Historical FS'!J6 -> 0.039664877 | K5: ='Historical FS'!K6 -> 0.059402946 | L5: ='Historical FS'!L6 -> 0.089514759
B6: EBITDA Growth | D6: ='Historical FS'!D18/'Historical FS'!C18-1 -> 0.0052304295 | E6: ='Historical FS'!E18/'Historical FS'!D18-1 -> 0.079609181 | F6: ='Historical FS'!F18/'Historical FS'!E18-1 -> 0.072882082 | G6: ='Historical FS'!G18/'Historical FS'!F18-1 -> 0.22071375 | H6: ='Historical FS'!H18/'Historical FS'!G18-1 -> 0.13783375 | I6: ='Historical FS'!I18/'Historical FS'!H18-1 -> 0.10298979 | J6: ='Historical FS'!J18/'Historical FS'!I18-1 -> 0.034632176 | K6: ='Historical FS'!K18/'Historical FS'!J18-1 -> 0.054854048 | L6: ='Historical FS'!L18/'Historical FS'!K18-1 -> 0.075047016
B7: PBT Growth | D7: ='Historical FS'!D31/'Historical FS'!C31-1 -> 0.05121977 | E7: ='Historical FS'!E31/'Historical FS'!D31-1 -> 0.00095439019 | F7: ='Historical FS'!F31/'Historical FS'!E31-1 -> 0.027600743 | G7: ='Historical FS'!G31/'Historical FS'!F31-1 -> 0.19534111 | H7: ='Historical FS'!H31/'Historical FS'!G31-1 -> 0.1641541 | I7: ='Historical FS'!I31/'Historical FS'!H31-1 -> 0.11047552 | J7: ='Historical FS'!J31/'Historical FS'!I31-1 -> 0.13620706 | K7: ='Historical FS'!K31/'Historical FS'!J31-1 -> -0.014240814 | L7: ='Historical FS'!L31/'Historical FS'!K31-1 -> 0.093563951
B8: Net profit Growth | D8: ='Historical FS'!D37/'Historical FS'!C37-1 -> 0.16912723 | E8: ='Historical FS'!E37/'Historical FS'!D37-1 -> -0.089941195 | F8: ='Historical FS'!F37/'Historical FS'!E37-1 -> 0.057203102 | G8: ='Historical FS'!G37/'Historical FS'!F37-1 -> 0.1611658 | H8: ='Historical FS'!H37/'Historical FS'!G37-1 -> 0.17658466 | I8: ='Historical FS'!I37/'Historical FS'!H37-1 -> 0.095738168 | J8: ='Historical FS'!J37/'Historical FS'!I37-1 -> 0.17044868 | K8: ='Historical FS'!K37/'Historical FS'!J37-1 -> -0.061173533 | L8: ='Historical FS'!L37/'Historical FS'!K37-1 -> 0.14248279
A11: # | B11: Gross Margin | C11: ='Historical FS'!C12 -> 0.35433217 | D11: ='Historical FS'!D12 -> 0.34888039 | E11: ='Historical FS'!E12 -> 0.33180133 | F11: ='Historical FS'!F12 -> 0.31701393 | G11: ='Historical FS'!G12 -> 0.32528634 | H11: ='Historical FS'!H12 -> 0.30810083 | I11: ='Historical FS'!I12 -> 0.28870128 | J11: ='Historical FS'!J12 -> 0.2877541 | ... L11: ='Historical FS'!L12 -> 0.28581028
B12: EBITDA Margin | C12: ='Historical FS'!C19 -> 0.29022247 | D12: ='Historical FS'!D19 -> 0.27924961 | E12: ='Historical FS'!E19 -> 0.25543382 | F12: ='Historical FS'!F19 -> 0.2534568 | G12: ='Historical FS'!G19 -> 0.28467502 | H12: ='Historical FS'!H19 -> 0.26773138 | I12: ='Historical FS'!I19 -> 0.24750431 | J12: ='Historical FS'!J19 -> 0.24630622 | ... L12: ='Historical FS'!L19 -> 0.24199195
B13: PBT Margin | C13: ='Historical FS'!C32 -> 0.31941844 | D13: ='Historical FS'!D32 -> 0.32140263 | E13: ='Historical FS'!E32 -> 0.27257308 | F13: ='Historical FS'!F32 -> 0.25904841 | G13: ='Historical FS'!G32 -> 0.28490781 | H13: ='Historical FS'!H32 -> 0.27414855 | I13: ='Historical FS'!I32 -> 0.25515668 | J13: ='Historical FS'!J32 -> 0.27885026 | ... L13: ='Historical FS'!L32 -> 0.26043046
B14: Net Margin | C14: ='Historical FS'!C37/'Historical FS'!C5 -> 0.23306178 | D14: ='Historical FS'!D37/'Historical FS'!D5 -> 0.26081271 | E14: ='Historical FS'!E37/'Historical FS'!E5 -> 0.20110249 | F14: ='Historical FS'!F37/'Historical FS'!F5 -> 0.19662985 | G14: ='Historical FS'!G37/'Historical FS'!G5 -> 0.21007543 | H14: ='Historical FS'!H37/'Historical FS'!H5 -> 0.20430056 | I14: ='Historical FS'!I37/'Historical FS'!I5 -> 0.18762398 | J14: ='Historical FS'!J37/'Historical FS'!J5 -> 0.21122599 | ... L14: ='Historical FS'!L37/'Historical FS'!L5 -> 0.19628542
A17: # | B17: Sales Expenses as a % of sales | C17: ='Historical FS'!C16 -> 0.0641097 | D17: ='Historical FS'!D16 -> 0.069630778 | E17: ='Historical FS'!E16 -> 0.076367516 | F17: ='Historical FS'!F16 -> 0.063557124 | G17: ='Historical FS'!G16 -> 0.040611323 | H17: ='Historical FS'!H16 -> 0.040369444 | I17: ='Historical FS'!I16 -> 0.041196962 | J17: ='Historical FS'!J16 -> 0.041447884 | ... L17: ='Historical FS'!L16 -> 0.04381833
B18: Depreciation as a % of sales | C18: ='Historical FS'!C25/'Historical FS'!C5 -> 0.022449358 | D18: ='Historical FS'!D25/'Historical FS'!D5 -> 0.022731309 | E18: ='Historical FS'!E25/'Historical FS'!E5 -> 0.021872051 | F18: ='Historical FS'!F25/'Historical FS'!F5 -> 0.027123104 | G18: ='Historical FS'!G25/'Historical FS'!G5 -> 0.027016016 | H18: ='Historical FS'!H25/'Historical FS'!H5 -> 0.023369251 | I18: ='Historical FS'!I25/'Historical FS'!I5 -> 0.022199107 | J18: ='Historical FS'!J25/'Historical FS'!J5 -> 0.022833565 | ... L18: ='Historical FS'!L25/'Historical FS'!L5 -> 0.016086656
B19: Operating income as a % of sales | C19: ='Historical FS'!C19 -> 0.29022247 | D19: ='Historical FS'!D19 -> 0.27924961 | E19: ='Historical FS'!E19 -> 0.25543382 | F19: ='Historical FS'!F19 -> 0.2534568 | G19: ='Historical FS'!G19 -> 0.28467502 | H19: ='Historical FS'!H19 -> 0.26773138 | I19: ='Historical FS'!I19 -> 0.24750431 | J19: ='Historical FS'!J19 -> 0.24630622 | ... L19: ='Historical FS'!L19 -> 0.24199195
B22: EBIT | C22: ='Historical FS'!C18-'Historical FS'!C25+'Historical FS'!C28 -> 18938 | D22: ='Historical FS'!D18-'Historical FS'!D25+'Historical FS'!D28 -> 19908 | E22: ='Historical FS'!E18-'Historical FS'!E25+'Historical FS'!E28 -> 19927 | F22: ='Historical FS'!F18-'Historical FS'!F25+'Historical FS'!F28 -> 20591 | G22: ='Historical FS'!G18-'Historical FS'!G25+'Historical FS'!G28 -> 24603 | H22: ='Historical FS'!H18-'Historical FS'!H25+'Historical FS'!H28 -> 28623 | I22: ='Historical FS'!I18-'Historical FS'!I25+'Historical FS'!I28 -> 31800 | J22: ='Historical FS'!J18-'Historical FS'!J25+'Historical FS'!J28 -> 36230 | ... L22: ='Historical FS'!L18-'Historical FS'!L25+'Historical FS'!L28 -> 38964
B23: Equity and debt | C23: =SUM('Historical FS'!C45:C47) -> 68017 | D23: =SUM('Historical FS'!D45:D47) -> 63502 | E23: =SUM('Historical FS'!E45:E47) -> 62711 | F23: =SUM('Historical FS'!F45:F47) -> 65399 | G23: =SUM('Historical FS'!G45:G47) -> 75385 | H23: =SUM('Historical FS'!H45:H47) -> 73092 | I23: =SUM('Historical FS'!I45:I47) -> 72011 | J23: =SUM('Historical FS'!J45:J47) -> 84942 | ... L23: =SUM('Historical FS'!L45:L47) -> 84623
A24: # | B24: Return on Capital employed | C24: =C22/C23 -> 0.27843039 | D24: =D22/D23 -> 0.31350194 | E24: =E22/E23 -> 0.31775924 | F24: =F22/F23 -> 0.31485191 | G24: =G22/G23 -> 0.32636466 | H24: =H22/H23 -> 0.39160236 | I24: =I22/I23 -> 0.4415992 | J24: =J22/J23 -> 0.42652634 | ... L24: =L22/L23 -> 0.4604422
B25: Retained Earnings | C25: ='Historical FS'!C41 -> 0.57213779 | D25: ='Historical FS'!D41 -> 0.41192201 | E25: ='Historical FS'!E41 -> 0.36298463 | F25: ='Historical FS'!F41 -> 0.52058805 | G25: ='Historical FS'!G41 -> 0.36269947 | H25: ='Historical FS'!H41 -> 0.3859854 | I25: ='Historical FS'!I41 -> 0.39388001 | J25: ='Historical FS'!J41 -> 0.29903797 | ... L25: ='Historical FS'!L41 -> 0.33383999
B26: ROE | C26: ='Historical FS'!C37/(SUM('Historical FS'!C45:C46)) -> 0.20315509 | D26: ='Historical FS'!D37/(SUM('Historical FS'!D45:D46)) -> 0.25440144 | E26: ='Historical FS'!E37/(SUM('Historical FS'!E45:E46)) -> 0.23444053 | F26: ='Historical FS'!F37/(SUM('Historical FS'!F45:F46)) -> 0.24975094 | G26: ='Historical FS'!G37/(SUM('Historical FS'!G45:G46)) -> 0.25231019 | H26: ='Historical FS'!H37/(SUM('Historical FS'!H45:H46)) -> 0.30639483 | I26: ='Historical FS'!I37/(SUM('Historical FS'!I45:I46)) -> 0.34346446 | J26: ='Historical FS'!J37/(SUM('Historical FS'!J45:J46)) -> 0.33549325 | ... L26: ='Historical FS'!L37/(SUM('Historical FS'!L45:L46)) -> 0.36119148
B27: Sustainable Growth rate | C27: =C25*C26 -> 0.11623271 | D27: =D25*D26 -> 0.10479355 | E27: =E25*E26 -> 0.085098308 | F27: =F25*F26 -> 0.13001735 | G27: =G25*G26 -> 0.091512771 | H27: =H25*H26 -> 0.11826393 | I27: =I25*I26 -> 0.13528378 | J27: =J25*J26 -> 0.10032522 | ... L27: =L25*L26 -> 0.12058016
B28: Interest Coverage ratio | C28: =IFERROR('Ratio Analysis'!C22/'Historical FS'!C22,"N.A") -> N.A | D28: =IFERROR('Ratio Analysis'!D22/'Historical FS'!D22,"N.A") -> N.A | E28: =IFERROR('Ratio Analysis'!E22/'Historical FS'!E22,"N.A") -> N.A | F28: =IFERROR('Ratio Analysis'!F22/'Historical FS'!F22,"N.A") -> 180.62281 | G28: =IFERROR('Ratio Analysis'!G22/'Historical FS'!G22,"N.A") -> 195.2619 | H28: =IFERROR('Ratio Analysis'!H22/'Historical FS'!H22,"N.A") -> 223.61719 | I28: =IFERROR('Ratio Analysis'!I22/'Historical FS'!I22,"N.A") -> 202.54777 | J28: =IFERROR('Ratio Analysis'!J22/'Historical FS'!J22,"N.A") -> 130.79422 | ... L28: =IFERROR('Ratio Analysis'!L22/'Historical FS'!L22,"N.A") -> 188.23188
A31: # | B31: Debtor Turnover Ratio | C31: ='Historical FS'!C5/'Historical FS'!C59 -> 5.4095803 | D31: ='Historical FS'!D5/'Historical FS'!D59 -> 5.0976051 | E31: ='Historical FS'!E5/'Historical FS'!E59 -> 5.467988 | F31: ='Historical FS'!F5/'Historical FS'!F59 -> 5.113332 | G31: ='Historical FS'!G5/'Historical FS'!G59 -> 5.2404538 | H31: ='Historical FS'!H5/'Historical FS'!H59 -> 5.4803332 | I31: ='Historical FS'!I5/'Historical FS'!I59 -> 5.969961 | J31: ='Historical FS'!J5/'Historical FS'!J59 -> 5.126153 | ... L31: ='Historical FS'!L5/'Historical FS'!L59 -> 4.9055279
B32: Creditor Turnover Ratio | C32: ='Historical FS'!C8/'Balance sheet'!C19 -> 308.71774 | D32: ='Historical FS'!D8/'Balance sheet'!D19 -> 64.736758 | E32: ='Historical FS'!E8/'Balance sheet'!E19 -> 181.59851 | F32: ='Historical FS'!F8/'Balance sheet'!F19 -> 73.154472 | G32: ='Historical FS'!G8/'Balance sheet'!G19 -> 36.138404 | H32: ='Historical FS'!H8/'Balance sheet'!H19 -> 47.034663 | I32: ='Historical FS'!I8/'Balance sheet'!I19 -> 56.473111 | J32: ='Historical FS'!J8/'Balance sheet'!J19 -> 34.406894 | ... L32: ='Historical FS'!L8/'Balance sheet'!L19 -> 42.633373
B33: Inventory Turnover Ratio
B34: Fixed Assets Turnover Ratio | C34: ='Historical FS'!C5/'Historical FS'!C53 -> 6.8900639 | D34: ='Historical FS'!D5/'Historical FS'!D53 -> 6.7643333 | E34: ='Historical FS'!E5/'Historical FS'!E53 -> 6.9645613 | F34: ='Historical FS'!F5/'Historical FS'!F53 -> 5.6567196 | G34: ='Historical FS'!G5/'Historical FS'!G53 -> 5.8847866 | H34: ='Historical FS'!H5/'Historical FS'!H53 -> 6.9580935 | I34: ='Historical FS'!I5/'Historical FS'!I53 -> 8.0366794 | J34: ='Historical FS'!J5/'Historical FS'!J53 -> 8.999302 | ... L34: ='Historical FS'!L5/'Historical FS'!L53 -> 10.755927
A37: # | B37: DAYS ( Assuming 360 days)
B38: Debtor | C38: =360/C31 -> 66.548601 | D38: =360/D31 -> 70.621398 | E38: =360/E31 -> 65.837745 | F38: =360/F31 -> 70.40419 | G38: =360/G31 -> 68.69634 | H38: =360/H31 -> 65.689436 | I38: =360/I31 -> 60.301901 | J38: =360/J31 -> 70.228103 | ... L38: =360/L31 -> 73.386597
B39: Creditors | C39: =360/C32 -> 1.1661137 | D39: =360/D32 -> 5.5609829 | E39: =360/E32 -> 1.9823951 | F39: =360/F32 -> 4.9210936 | G39: =360/G32 -> 9.9617017 | H39: =360/H32 -> 7.6539296 | I39: =360/I32 -> 6.3747152 | J39: =360/J32 -> 10.463019 | ... L39: =360/L32 -> 8.444089
B40: Inventory
B41: Cash Conversion Cycle
A44: # | B44: CFO/Sales | C44: ='Historical FS'!C74/'Historical FS'!C5 -> 0.17672755 | D44: ='Historical FS'!D74/'Historical FS'!D5 -> 0.20140133 | E44: ='Historical FS'!E74/'Historical FS'!E5 -> 0.19134967 | F44: ='Historical FS'!F74/'Historical FS'!F5 -> 0.19699672 | G44: ='Historical FS'!G74/'Historical FS'!G5 -> 0.23165565 | H44: ='Historical FS'!H74/'Historical FS'!H5 -> 0.21258418 | I44: ='Historical FS'!I74/'Historical FS'!I5 -> 0.15457126 | J44: ='Historical FS'!J74/'Historical FS'!J5 -> 0.16122327 | ... L44: ='Historical FS'!L74/'Historical FS'!L5 -> 0.18925003
B45: CFO/Total Assets | C45: ='Historical FS'!C74/'Historical FS'!C66 -> 0.13116355 | D45: ='Historical FS'!D74/'Historical FS'!D66 -> 0.16551239 | E45: ='Historical FS'!E74/'Historical FS'!E66 -> 0.17845616 | F45: ='Historical FS'!F74/'Historical FS'!F66 -> 0.19347705 | G45: ='Historical FS'!G74/'Historical FS'!G66 -> 0.21301965 | H45: ='Historical FS'!H74/'Historical FS'!H66 -> 0.22422016 | I45: ='Historical FS'!I74/'Historical FS'!I66 -> 0.19062631 | J45: ='Historical FS'!J74/'Historical FS'!J66 -> 0.18083515 | ... L45: ='Historical FS'!L74/'Historical FS'!L66 -> 0.2240555
B46: CFO/Debt | C46: =IFERROR('Historical FS'!C74/'Historical FS'!C47,"N.A") -> N.A | D46: =IFERROR('Historical FS'!D74/'Historical FS'!D47,"N.A") -> N.A | E46: =IFERROR('Historical FS'!E74/'Historical FS'!E47,"N.A") -> N.A | F46: =IFERROR('Historical FS'!F74/'Historical FS'!F47,"N.A") -> 4.9200632 | G46: =IFERROR('Historical FS'!G74/'Historical FS'!G47,"N.A") -> 5.1639855 | H46: =IFERROR('Historical FS'!H74/'Historical FS'!H47,"N.A") -> 5.8362388 | I46: =IFERROR('Historical FS'!I74/'Historical FS'!I47,"N.A") -> 4.4934365 | J46: =IFERROR('Historical FS'!J74/'Historical FS'!J47,"N.A") -> 5.5196495 | ... L46: =IFERROR('Historical FS'!L74/'Historical FS'!L47,"N.A") -> 7.5124033

Sheet Dupont
B2: ='DATA Sheet'!B1&" Dupont" -> INFOSYS LTD Dupont
B3: Years | C3: FY17 | D3: FY18 | E3: FY19 | F3: FY20 | G3: FY21 | H3: FY22 | I3: FY23 | J3: FY24 | K3: FY25 | L3: FY26
B4: Net margin | C4: ='Ratio Analysis'!C14 -> 0.23306178 | D4: ='Ratio Analysis'!D14 -> 0.26081271 | E4: ='Ratio Analysis'!E14 -> 0.20110249 | F4: ='Ratio Analysis'!F14 -> 0.19662985 | G4: ='Ratio Analysis'!G14 -> 0.21007543 | H4: ='Ratio Analysis'!H14 -> 0.20430056 | I4: ='Ratio Analysis'!I14 -> 0.18762398 | J4: ='Ratio Analysis'!J14 -> 0.21122599 | ... L4: ='Ratio Analysis'!L14 -> 0.19628542
B5: Asset turnover | C5: ='Historical FS'!C5/'Historical FS'!C66 -> 0.74217938 | D5: ='Historical FS'!D5/'Historical FS'!D66 -> 0.82180385 | E5: ='Historical FS'!E5/'Historical FS'!E66 -> 0.9326181 | F5: ='Historical FS'!F5/'Historical FS'!F66 -> 0.98213332 | G5: ='Historical FS'!G5/'Historical FS'!G66 -> 0.91955302 | H5: ='Historical FS'!H5/'Historical FS'!H66 -> 1.0547359 | I5: ='Historical FS'!I5/'Historical FS'!I66 -> 1.2332584 | J5: ='Historical FS'!J5/'Historical FS'!J66 -> 1.1216442 | ... L5: ='Historical FS'!L5/'Historical FS'!L66 -> 1.1839126
B6: Fin Lev | C6: ='Historical FS'!C66/SUM('Historical FS'!C45:C46) -> 1.1744858 | D6: ='Historical FS'!D66/SUM('Historical FS'!D45:D46) -> 1.1869232 | E6: ='Historical FS'!E66/SUM('Historical FS'!E45:E46) -> 1.250004 | F6: ='Historical FS'!F66/SUM('Historical FS'!F45:F46) -> 1.2932641 | G6: ='Historical FS'!G66/SUM('Historical FS'!G45:G46) -> 1.306119 | H6: ='Historical FS'!H66/SUM('Historical FS'!H45:H46) -> 1.4218971 | I6: ='Historical FS'!I66/SUM('Historical FS'!I45:I46) -> 1.4843605 | J6: ='Historical FS'!J66/SUM('Historical FS'!J45:J46) -> 1.4160589 | ... L6: ='Historical FS'!L66/SUM('Historical FS'!L45:L46) -> 1.554282
B8: ROE | C8: =PRODUCT(C4:C6) -> 0.20315509 | D8: =PRODUCT(D4:D6) -> 0.25440144 | E8: =PRODUCT(E4:E6) -> 0.23444053 | F8: =PRODUCT(F4:F6) -> 0.24975094 | G8: =PRODUCT(G4:G6) -> 0.25231019 | H8: =PRODUCT(H4:H6) -> 0.30639483 | I8: =PRODUCT(I4:I6) -> 0.34346446 | J8: =PRODUCT(J4:J6) -> 0.33549325 | ... L8: =PRODUCT(L4:L6) -> 0.36119148

Sheet KPIs
B2: ='DATA Sheet'!B1&" KPIs" -> INFOSYS LTD KPIs
B3: Years | C3: FY16 | D3: FY17 | E3: FY18 | F3: FY19 | G3: FY20 | H3: FY21 | I3: FY22 | J3: FY23 | K3: FY24 | L3: FY25 | M3: FY26
B4: Active Clients | C4: 1092 | D4: 1162 | E4: 1204 | F4: 1279 | G4: 1411 | H4: 1626 | I4: 1741 | J4: 1872 | K4: 1882 | L4: 1869 | M4: 1965
B5: Mega Clients ($100M+ revenue) | C5: 14 | D5: 19 | E5: 20 | F5: 25 | G5: 28 | H5: 32 | I5: 38 | J5: 40 | K5: 40 | L5: 42 | M5: 45
B6: Total Headcount | C6: 194044 | D6: 200364 | E6: 204107 | F6: 228123 | G6: 242371 | H6: 259619 | I6: 314015 | J6: 343234 | K6: 317240 | L6: 323578 | M6: 328594
B7: Large Deal Total Contract Value (TCV)(USD Bn) | C7: 2.8 | D7: 3.5 | F7: 6.3 | G7: 9 | H7: 14 | I7: 9.5 | J7: 9.8 | K7: 17.7 | L7: 11.6 | M7: 14.9
B8: Voluntary Attrition (LTM, IT Services)% | C8: 13.6 | D8: 15 | E8: 16.4 | G8: 17.4 | H8: 10.9 | I8: 27.7 | J8: 20.9 | K8: 12.6 | L8: 14.1 | M8: 12.6
B9: Large Clients ($50M+ revenue) | D9: 56 | E9: 57 | F9: 60 | J9: 75 | K9: 83 | L9: 85 | M9: 88
B10: Freshers Hired | H10: 19000 | I10: 60405 | J10: 50000 | K10: 11900 | L10: 15288 | M10: 20000
B11: Utilization (Excluding Trainees) % | C11: 80.8 | D11: 81.7 | E11: 84.6 | F11: 84.3 | G11: 84 | M11: 84.4
B12: Onsite Mix | D12: 53.7 | E12: 55.4 | F12: 54.9 | G12: 54.8
B13: R&D Expenditure (Percentage of Turnover) | C13: 0.8 | D13: 0.6 | E13: 0.6 | F13: 0.6 | G13: 0.6 | H13: 0.6 | I13: 0.5 | J13: 0.5 | K13: 0.54 | L13: 0.62
B16: Sales per Client for FY16 | C16: ='P&L'!D4/KPIs!C4 -> 49.434982
B17: Avg employee cost | C17: =0.5227*'P&L'!D5 -> 20005.82 | D17: =C17/C6 -> 0.1030994

Sheet Scenarios>>

Sheet Scenarios
D5: Particulars | E5: Pessmistic | F5: Base | G5: Optmistic | H5: Choose
D6: GDP growth | E6: -0.02 | F6: 0 | G6: 0.02 | H6: =INDEX($E6:$G6,MATCH(DASHBOARD!$D$2,Scenarios!$E$5:$G$5,0)) -> 0
D7: Headcount | E7: -0.02 | F7: 0 | G7: 0.01 | H7: =INDEX($E7:$G7,MATCH(DASHBOARD!$D$2,Scenarios!$E$5:$G$5,0)) -> 0
D8: Avg Employee cost | E8: 0.02 | F8: 0 | G8: -0.02 | H8: =INDEX($E8:$G8,MATCH(DASHBOARD!$D$2,Scenarios!$E$5:$G$5,0)) -> 0
D9: Active Clients | E9: -0.03 | F9: 0 | G9: 0.02 | H9: =INDEX($E9:$G9,MATCH(DASHBOARD!$D$2,Scenarios!$E$5:$G$5,0)) -> 0
D10: Sales Per client | E10: -0.015 | F10: 0 | G10: 0.02 | H10: =INDEX($E10:$G10,MATCH(DASHBOARD!$D$2,Scenarios!$E$5:$G$5,0)) -> 0
D11: Large clients | E11: -0.015 | F11: 0 | G11: 0.015 | H11: =INDEX($E11:$G11,MATCH(DASHBOARD!$D$2,Scenarios!$E$5:$G$5,0)) -> 0
D12: Other Clients | E12: -0.015 | F12: 0 | G12: 0.015 | H12: =INDEX($E12:$G12,MATCH(DASHBOARD!$D$2,Scenarios!$E$5:$G$5,0)) -> 0

Sheet Forecast>>

Sheet Forecast Drivers
B2: ='DATA Sheet'!B1&" Forecast Assumptions" -> INFOSYS LTD Forecast Assumptions
B3: Year Weights | C3: 1 | D3: =C3+1 -> 2 | E3: =D3+1 -> 3 | F3: =E3+1 -> 4 | G3: =F3+1 -> 5 | H3: =G3+1 -> 6 | I3: =H3+1 -> 7 | J3: =I3+1 -> 8 | K3: =J3+1 -> 9 | ... Q3: =P3+1 -> 15
B4: Years (As on March) | C4: 2017 | D4: =C4+1 -> 2018 | E4: =D4+1 -> 2019 | F4: =E4+1 -> 2020 | G4: =F4+1 -> 2021 | H4: =G4+1 -> 2022 | I4: =H4+1 -> 2023 | J4: =I4+1 -> 2024 | K4: =J4+1 -> 2025 | ... Q4: =P4+1 -> 2031
A6: # | B6: Revenue Drivers
B7: Sales | C7: ='Historical FS'!C5 -> 59289 | D7: ='Historical FS'!D5 -> 61941 | E7: ='Historical FS'!E5 -> 73107 | F7: ='Historical FS'!F5 -> 79047 | G7: ='Historical FS'!G5 -> 85912 | H7: ='Historical FS'!H5 -> 103940 | I7: ='Historical FS'!I5 -> 124014 | J7: ='Historical FS'!J5 -> 128933 | ... L7: ='Historical FS'!L5 -> 148819 | M7: =M12*M9 -> 160489.88 | N7: =N12*N9 -> 173076.03 | O7: =O12*O9 -> 186649.22 | P7: =P12*P9 -> 201286.87 | Q7: =Q12*Q9 -> 217072.46
B9: Active Clients | C9: =KPIs!D4 -> 1162 | D9: =KPIs!E4 -> 1204 | E9: =KPIs!F4 -> 1279 | F9: =KPIs!G4 -> 1411 | G9: =KPIs!H4 -> 1626 | H9: =KPIs!I4 -> 1741 | I9: =KPIs!J4 -> 1872 | J9: =KPIs!K4 -> 1882 | ... L9: =KPIs!M4 -> 1965 | M9: =L9*(1+M10) -> 2026.4273 | N9: =M9*(1+N10) -> 2089.7748 | O9: =N9*(1+O10) -> 2155.1027 | P9: =O9*(1+P10) -> 2222.4727 | Q9: =P9*(1+Q10) -> 2291.9487
B10: % growth | C10: =C9/KPIs!C4-1 -> 0.064102564 | D10: =D9/C9-1 -> 0.036144578 | E10: =E9/D9-1 -> 0.062292359 | F10: =F9/E9-1 -> 0.10320563 | G10: =G9/F9-1 -> 0.1523742 | H10: =H9/G9-1 -> 0.070725707 | I10: =I9/H9-1 -> 0.075244113 | J10: =J9/I9-1 -> 0.0053418803 | K10: =K9/J9-1 -> -0.0069075452 | L10: =L9/K9-1 -> 0.051364366 | M10: =AVERAGE($I10:$L10)+Scenarios!$H$9 -> 0.031260703 | N10: =AVERAGE($I10:$L10)+Scenarios!$H$9 -> 0.031260703 | O10: =AVERAGE($I10:$L10)+Scenarios!$H$9 -> 0.031260703 | P10: =AVERAGE($I10:$L10)+Scenarios!$H$9 -> 0.031260703 | Q10: =AVERAGE($I10:$L10)+Scenarios!$H$9 -> 0.031260703
B12: sales per Client | C12: =C7/C9 -> 51.023236 | D12: =D7/D9 -> 51.446013 | E12: =E7/E9 -> 57.1595 | F12: =F7/F9 -> 56.02197 | G12: =G7/G9 -> 52.836408 | H12: =H7/H9 -> 59.701321 | I12: =I7/I9 -> 66.246795 | J12: =J7/J9 -> 68.508502 | ... L12: =L7/L9 -> 75.73486 | M12: =L12*(1+M13) -> 79.19844 | N12: =M12*(1+N13) -> 82.820419 | O12: =N12*(1+O13) -> 86.608043 | P12: =O12*(1+P13) -> 90.568885 | Q12: =P12*(1+Q13) -> 94.710869
B13: Growth | C13: =C12/KPIs!C16-1 -> 0.032128142 | D13: =D12/C12-1 -> 0.0082859796 | E13: =E12/D12-1 -> 0.1110579 | F13: =F12/E12-1 -> -0.019900968 | G13: =G12/F12-1 -> -0.056862725 | H13: =H12/G12-1 -> 0.12992769 | I13: =I12/H12-1 -> 0.109637 | J13: =J12/I12-1 -> 0.034140621 | K13: =K12/J12-1 -> 0.06677172 | L13: =L12/K12-1 -> 0.036286557 | M13: =AVERAGE($J13:$L13)+Scenarios!$H$10 -> 0.045732966 | N13: =AVERAGE($J13:$L13)+Scenarios!$H$10 -> 0.045732966 | O13: =AVERAGE($J13:$L13)+Scenarios!$H$10 -> 0.045732966 | P13: =AVERAGE($J13:$L13)+Scenarios!$H$10 -> 0.045732966 | Q13: =AVERAGE($J13:$L13)+Scenarios!$H$10 -> 0.045732966
B16: Large and Mega Client | C16: =KPIs!D5+KPIs!D9 -> 75 | D16: =KPIs!E5+KPIs!E9 -> 77 | E16: =KPIs!F5+KPIs!F9 -> 85 | F16: =KPIs!G5+KPIs!G9 -> 28 | G16: =KPIs!H5+KPIs!H9 -> 32 | H16: =KPIs!I5+KPIs!I9 -> 38 | I16: =KPIs!J5+KPIs!J9 -> 115 | J16: =KPIs!K5+KPIs!K9 -> 123 | ... L16: =KPIs!M5+KPIs!M9 -> 133 | M16: =L16*(1+M17) -> 139.62028 | N16: =M16*(1+N17) -> 146.5701 | O16: =N16*(1+O17) -> 153.86585 | P16: =O16*(1+P17) -> 161.52476 | Q16: =P16*(1+Q17) -> 169.5649
B17: Growth | C17: =C16/(KPIs!C5+KPIs!C9) -> 5.3571429 | D17: =D16/C16-1 -> 0.026666667 | E17: =E16/D16-1 -> 0.1038961 | F17: =F16/E16-1 -> -0.67058824 | G17: =G16/F16-1 -> 0.14285714 | H17: =H16/G16-1 -> 0.1875 | I17: =I16/H16-1 -> 2.0263158 | J17: =J16/I16-1 -> 0.069565217 | K17: =K16/J16-1 -> 0.032520325 | L17: =L16/K16-1 -> 0.047244094 | M17: =AVERAGE($J17:$L17)+Scenarios!$H$11 -> 0.049776546 | N17: =AVERAGE($J17:$L17)+Scenarios!$H$11 -> 0.049776546 | O17: =AVERAGE($J17:$L17)+Scenarios!$H$11 -> 0.049776546 | P17: =AVERAGE($J17:$L17)+Scenarios!$H$11 -> 0.049776546 | Q17: =AVERAGE($J17:$L17)+Scenarios!$H$11 -> 0.049776546
B19: % of total client | C19: =C16/C9 -> 0.06454389 | D19: =D16/D9 -> 0.063953488 | E19: =E16/E9 -> 0.06645817 | F19: =F16/F9 -> 0.019844082 | G19: =G16/G9 -> 0.019680197 | H19: =H16/H9 -> 0.021826536 | I19: =I16/I9 -> 0.061431624 | J19: =J16/J9 -> 0.065356004 | ... L19: =L16/L9 -> 0.067684478 | M19: =AVERAGE($J19:$L19) -> 0.066997086 | N19: =AVERAGE($J19:$L19) -> 0.066997086 | O19: =AVERAGE($J19:$L19) -> 0.066997086 | P19: =AVERAGE($J19:$L19) -> 0.066997086 | Q19: =AVERAGE($J19:$L19) -> 0.066997086
B20: Large & mega Sales | C20: =C19*C7 -> 3826.7427 | D20: =D19*D7 -> 3961.343 | E20: =E19*E7 -> 4858.5575 | F20: =F19*F7 -> 1568.6152 | G20: =G19*G7 -> 1690.7651 | H20: =H19*H7 -> 2268.6502 | I20: =I19*I7 -> 7618.3814 | J20: =J19*J7 -> 8426.5457 | ... Q20: =Q19*Q7 -> 14543.222
B23: Other Client | C23: =C9-C16 -> 1087 | D23: =D9-D16 -> 1127 | E23: =E9-E16 -> 1194 | F23: =F9-F16 -> 1383 | G23: =G9-G16 -> 1594 | H23: =H9-H16 -> 1703 | I23: =I9-I16 -> 1757 | J23: =J9-J16 -> 1759 | ... L23: =L9-L16 -> 1832 | M23: =L23*(1+M24) -> 1926.6498 | N23: =M23*(1+N24) -> 2026.1897 | O23: =N23*(1+O24) -> 2130.8723 | P23: =O23*(1+P24) -> 2240.9633 | Q23: =P23*(1+Q24) -> 2356.7421
B24: Growth | C24: =C23/(KPIs!C4-KPIs!C5-KPIs!C9)-1 -> 0.0083487941 | D24: =D23/C23-1 -> 0.036798528 | E24: =E23/D23-1 -> 0.059449867 | F24: =F23/E23-1 -> 0.15829146 | G24: =G23/F23-1 -> 0.15256688 | H24: =H23/G23-1 -> 0.06838143 | I24: =I23/H23-1 -> 0.031708749 | J24: =J23/I23-1 -> 0.0011383039 | K24: =K23/J23-1 -> -0.0096645821 | L24: =L23/K23-1 -> 0.051664753 | M24: =L24+Scenarios!$H$12 -> 0.051664753 | N24: =M24+Scenarios!$H$12 -> 0.051664753 | O24: =N24+Scenarios!$H$12 -> 0.051664753 | P24: =O24+Scenarios!$H$12 -> 0.051664753 | Q24: =P24+Scenarios!$H$12 -> 0.051664753
B26: % of total client | C26: =1-C19 -> 0.93545611 | D26: =1-D19 -> 0.93604651 | E26: =1-E19 -> 0.93354183 | F26: =1-F19 -> 0.98015592 | G26: =1-G19 -> 0.9803198 | H26: =1-H19 -> 0.97817346 | I26: =1-I19 -> 0.93856838 | J26: =1-J19 -> 0.934644 | ... Q26: =1-Q19 -> 0.93300291
B27: Other Client sales | C27: =C26*C7 -> 55462.257 | D27: =D26*D7 -> 57979.657 | E27: =E26*E7 -> 68248.443 | F27: =F26*F7 -> 77478.385 | G27: =G26*G7 -> 84221.235 | H27: =H26*H7 -> 101671.35 | I27: =I26*I7 -> 116395.62 | J27: =J26*J7 -> 120506.45 | ... Q27: =Q26*Q7 -> 202529.24
A30: # | B30: Cost Driver
B32: COGS | C32: ='Historical FS'!C8 -> 38281 | D32: ='Historical FS'!D8 -> 40331 | E32: ='Historical FS'!E8 -> 48850 | F32: ='Historical FS'!F8 -> 53988 | G32: ='Historical FS'!G8 -> 57966 | H32: ='Historical FS'!H8 -> 71916 | I32: ='Historical FS'!I8 -> 88211 | J32: ='Historical FS'!J8 -> 91832 | ... L32: ='Historical FS'!L8 -> 106285 | M32: =M34+M43 -> 113755.42 | N32: =N34+N43 -> 121772.55 | O32: =O34+O43 -> 130378.12 | P32: =P34+P43 -> 139617.15 | Q32: =Q34+Q43 -> 149538.27
B34: Employee Cost | C34: ='DATA Sheet'!B22 -> 30953 | D34: ='DATA Sheet'!C22 -> 32481 | E34: ='DATA Sheet'!D22 -> 38303 | F34: ='DATA Sheet'!E22 -> 42442 | G34: ='DATA Sheet'!F22 -> 45185 | H34: ='DATA Sheet'!G22 -> 51675 | I34: ='DATA Sheet'!H22 -> 62779 | J34: ='DATA Sheet'!I22 -> 65155 | ... L34: ='DATA Sheet'!K22 -> 73257 | M34: =M39*M36 -> 77704.122 | N34: =N39*N36 -> 82421.21 | O34: =O39*O36 -> 87424.653 | P34: =P39*P36 -> 92731.833 | Q34: =Q39*Q36 -> 98361.19
B36: Head Count | C36: =KPIs!D6 -> 200364 | D36: =KPIs!E6 -> 204107 | E36: =KPIs!F6 -> 228123 | F36: =KPIs!G6 -> 242371 | G36: =KPIs!H6 -> 259619 | H36: =KPIs!I6 -> 314015 | I36: =KPIs!J6 -> 343234 | J36: =KPIs!K6 -> 317240 | ... L36: =KPIs!M6 -> 328594 | M36: =L36*(1+M37) -> 334423.3 | N36: =M36*(1+N37) -> 340356.01 | O36: =N36*(1+O37) -> 346393.96 | P36: =O36*(1+P37) -> 352539.03 | Q36: =P36*(1+Q37) -> 358793.12
B37: Growth | C37: =C36/KPIs!C6-1 -> 0.032569933 | D37: =D36/C36-1 -> 0.018681001 | E37: =E36/D36-1 -> 0.11766377 | F37: =F36/E36-1 -> 0.062457534 | G37: =G36/F36-1 -> 0.071163629 | H37: =H36/G36-1 -> 0.20952242 | I37: =I36/H36-1 -> 0.093049695 | J37: =J36/I36-1 -> -0.075732591 | K37: =K36/J36-1 -> 0.019978565 | L37: =L36/K36-1 -> 0.015501672 | M37: =AVERAGE($K37:$L37)+Scenarios!$H$7 -> 0.017740119 | N37: =AVERAGE($K37:$L37)+Scenarios!$H$7 -> 0.017740119 | O37: =AVERAGE($K37:$L37)+Scenarios!$H$7 -> 0.017740119 | P37: =AVERAGE($K37:$L37)+Scenarios!$H$7 -> 0.017740119 | Q37: =AVERAGE($K37:$L37)+Scenarios!$H$7 -> 0.017740119
B39: Avereage Employee cost\ | C39: =C34/C36 -> 0.15448384 | D39: =D34/D36 -> 0.15913712 | E39: =E34/E36 -> 0.16790503 | F39: =F34/F36 -> 0.17511171 | G39: =G34/G36 -> 0.1740435 | H39: =H34/H36 -> 0.1645622 | I39: =I34/I36 -> 0.18290437 | J39: =J34/J36 -> 0.20538078 | ... L39: =L34/L36 -> 0.22294077 | M39: =L39*(1+M40) -> 0.2323526 | N39: =M39*(1+N40) -> 0.24216176 | O39: =N39*(1+O40) -> 0.25238504 | P39: =O39*(1+P40) -> 0.2630399 | Q39: =P39*(1+Q40) -> 0.27414459
B40: Growth | C40: =C39/KPIs!D17-1 -> 0.49839709 | D40: =D39/C39-1 -> 0.030121467 | E40: =E39/D39-1 -> 0.055096601 | F40: =F39/E39-1 -> 0.042921139 | G40: =G39/F39-1 -> -0.0061001443 | H40: =H39/G39-1 -> -0.054476609 | I40: =I39/H39-1 -> 0.11146042 | J40: =J39/I39-1 -> 0.12288613 | K40: =K39/J39-1 -> 0.015458133 | L40: =L39/K39-1 -> 0.068975299 | M40: =AVERAGE($K40:$L40)+Scenarios!$H$8 -> 0.042216716 | N40: =AVERAGE($K40:$L40)+Scenarios!$H$8 -> 0.042216716 | O40: =AVERAGE($K40:$L40)+Scenarios!$H$8 -> 0.042216716 | P40: =AVERAGE($K40:$L40)+Scenarios!$H$8 -> 0.042216716 | Q40: =AVERAGE($K40:$L40)+Scenarios!$H$8 -> 0.042216716
B43: Other COGS | C43: =C32-C34 -> 7328 | D43: =D32-D34 -> 7850 | E43: =E32-E34 -> 10547 | F43: =F32-F34 -> 11546 | G43: =G32-G34 -> 12781 | H43: =H32-H34 -> 20241 | I43: =I32-I34 -> 25432 | J43: =J32-J34 -> 26677 | ... L43: =L32-L34 -> 33028 | M43: =L43*(1+M44) -> 36051.299 | N43: =M43*(1+N44) -> 39351.343 | O43: =N43*(1+O44) -> 42953.465 | P43: =O43*(1+P44) -> 46885.316 | Q43: =P43*(1+Q44) -> 51177.078
C44: =C43/'P&L'!D18-1 -> 0.027154327 | D44: =D43/C43-1 -> 0.071233624 | E44: =E43/D43-1 -> 0.34356688 | F44: =F43/E43-1 -> 0.094718877 | G44: =G43/F43-1 -> 0.10696345 | H44: =H43/G43-1 -> 0.5836789 | I44: =I43/H43-1 -> 0.25645966 | J44: =J43/I43-1 -> 0.048954074 | K44: =K43/J43-1 -> 0.13067436 | L44: =L43/K43-1 -> 0.094983921 | M44: =AVERAGE($J44:$L44) -> 0.091537453 | N44: =AVERAGE($J44:$L44) -> 0.091537453 | O44: =AVERAGE($J44:$L44) -> 0.091537453 | P44: =AVERAGE($J44:$L44) -> 0.091537453 | Q44: =AVERAGE($J44:$L44) -> 0.091537453
B47: SG&A | C47: ='Historical FS'!C15 -> 3801 | D47: ='Historical FS'!D15 -> 4313 | E47: ='Historical FS'!E15 -> 5583 | F47: ='Historical FS'!F15 -> 5024 | G47: ='Historical FS'!G15 -> 3489 | H47: ='Historical FS'!H15 -> 4196 | I47: ='Historical FS'!I15 -> 5109 | J47: ='Historical FS'!J15 -> 5344 | ... L47: ='Historical FS'!L15 -> 6521 | M47: =M48*M7 -> 6694.3954 | N47: =N48*N7 -> 7219.3921 | O47: =O48*O7 -> 7785.5607 | P47: =P48*P7 -> 8396.1302 | Q47: =Q48*Q7 -> 9054.5826
B48: % of sales | C48: =C47/C7 -> 0.0641097 | D48: =D47/D7 -> 0.069630778 | E48: =E47/E7 -> 0.076367516 | F48: =F47/F7 -> 0.063557124 | G48: =G47/G7 -> 0.040611323 | H48: =H47/H7 -> 0.040369444 | I48: =I47/I7 -> 0.041196962 | J48: =J47/J7 -> 0.041447884 | ... L48: =L47/L7 -> 0.04381833 | M48: =AVERAGE($J48:$L48) -> 0.041712259 | N48: =AVERAGE($J48:$L48) -> 0.041712259 | O48: =AVERAGE($J48:$L48) -> 0.041712259 | P48: =AVERAGE($J48:$L48) -> 0.041712259 | Q48: =AVERAGE($J48:$L48) -> 0.041712259
A51: # | B51: Depreciation
B53: Fixed Assets | C53: ='Historical FS'!C53 -> 8605 | D53: ='Historical FS'!D53 -> 9157 | E53: ='Historical FS'!E53 -> 10497 | F53: ='Historical FS'!F53 -> 13974 | G53: ='Historical FS'!G53 -> 14599 | H53: ='Historical FS'!H53 -> 14938 | I53: ='Historical FS'!I53 -> 15431 | J53: ='Historical FS'!J53 -> 14327 | ... L53: ='Historical FS'!L53 -> 13836 | M53: =M7/M54 -> 16059.723 | N53: =N7/N54 -> 17319.18 | O53: =O7/O54 -> 18677.408 | P53: =P7/P54 -> 20142.152 | Q53: =Q7/Q54 -> 21721.766
B54: FA turnover ratio | C54: ='Ratio Analysis'!C34 -> 6.8900639 | D54: ='Ratio Analysis'!D34 -> 6.7643333 | E54: ='Ratio Analysis'!E34 -> 6.9645613 | F54: ='Ratio Analysis'!F34 -> 5.6567196 | G54: ='Ratio Analysis'!G34 -> 5.8847866 | H54: ='Ratio Analysis'!H34 -> 6.9580935 | I54: ='Ratio Analysis'!I34 -> 8.0366794 | J54: ='Ratio Analysis'!J34 -> 8.999302 | ... L54: ='Ratio Analysis'!L34 -> 10.755927 | M54: =AVERAGE($J54:$L54) -> 9.9933153 | N54: =AVERAGE($J54:$L54) -> 9.9933153 | O54: =AVERAGE($J54:$L54) -> 9.9933153 | P54: =AVERAGE($J54:$L54) -> 9.9933153 | Q54: =AVERAGE($J54:$L54) -> 9.9933153
B56: Depreciation | C56: ='Historical FS'!C25 -> 1331 | D56: ='Historical FS'!D25 -> 1408 | E56: ='Historical FS'!E25 -> 1599 | F56: ='Historical FS'!F25 -> 2144 | G56: ='Historical FS'!G25 -> 2321 | H56: ='Historical FS'!H25 -> 2429 | I56: ='Historical FS'!I25 -> 2753 | J56: ='Historical FS'!J25 -> 2944 | ... L56: ='Historical FS'!L25 -> 2394 | M56: =M57*M7 -> 3107.8389 | N56: =N57*N7 -> 3351.566 | O56: =O57*O7 -> 3614.4069 | P56: =P57*P7 -> 3897.8606 | Q56: =Q57*Q7 -> 4203.5438
B57: % of sales | C57: =C56/C7 -> 0.022449358 | D57: =D56/D7 -> 0.022731309 | E57: =E56/E7 -> 0.021872051 | F57: =F56/F7 -> 0.027123104 | G57: =G56/G7 -> 0.027016016 | H57: =H56/H7 -> 0.023369251 | I57: =I56/I7 -> 0.022199107 | J57: =J56/J7 -> 0.022833565 | ... L57: =L56/L7 -> 0.016086656 | M57: =AVERAGE($J57:$L57) -> 0.019364703 | N57: =AVERAGE($J57:$L57) -> 0.019364703 | O57: =AVERAGE($J57:$L57) -> 0.019364703 | P57: =AVERAGE($J57:$L57) -> 0.019364703 | Q57: =AVERAGE($J57:$L57) -> 0.019364703
A60: # | B60: borrowings
B62: Borrowings | C62: ='Historical FS'!C47 -> 0 | D62: ='Historical FS'!D47 -> 0 | E62: ='Historical FS'!E47 -> 0 | F62: ='Historical FS'!F47 -> 3165 | G62: ='Historical FS'!G47 -> 3854 | H62: ='Historical FS'!H47 -> 3786 | I62: ='Historical FS'!I47 -> 4266 | J62: ='Historical FS'!J47 -> 3766 | ... L62: ='Historical FS'!L47 -> 3749 | M62: =AVERAGE($J$62:$L$62) -> 3658 | N62: =AVERAGE($J$62:$L$62) -> 3658 | O62: =AVERAGE($J$62:$L$62) -> 3658 | P62: =AVERAGE($J$62:$L$62) -> 3658 | Q62: =AVERAGE($J$62:$L$62) -> 3658
B65: Interest | C65: ='Historical FS'!C22 -> 0 | D65: ='Historical FS'!D22 -> 0 | E65: ='Historical FS'!E22 -> 0 | F65: ='Historical FS'!F22 -> 114 | G65: ='Historical FS'!G22 -> 126 | H65: ='Historical FS'!H22 -> 128 | I65: ='Historical FS'!I22 -> 157 | J65: ='Historical FS'!J22 -> 277 | ... L65: ='Historical FS'!L22 -> 207 | M65: =M66*M62 -> 234.91537 | N65: =N66*N62 -> 234.91537 | O65: =O66*O62 -> 234.91537 | P65: =P66*P62 -> 234.91537 | Q65: =Q66*Q62 -> 234.91537
B66: Effective rate | F66: =F65/F62 -> 0.036018957 | G66: =G65/G62 -> 0.032693306 | H66: =H65/H62 -> 0.033808769 | I66: =I65/I62 -> 0.036802625 | J66: =J65/J62 -> 0.073552841 | K66: =K65/K62 -> 0.063891298 | L66: =L65/L62 -> 0.055214724 | M66: =AVERAGE($J66:$L66) -> 0.064219621 | N66: =AVERAGE($J66:$L66) -> 0.064219621 | O66: =AVERAGE($J66:$L66) -> 0.064219621 | P66: =AVERAGE($J66:$L66) -> 0.064219621 | Q66: =AVERAGE($J66:$L66) -> 0.064219621
A69: # | B69: Others
B71: Other Income | C71: ='Historical FS'!C28 -> 3062 | D71: ='Historical FS'!D28 -> 4019 | E71: ='Historical FS'!E28 -> 2852 | F71: ='Historical FS'!F28 -> 2700 | G71: ='Historical FS'!G28 -> 2467 | H71: ='Historical FS'!H28 -> 3224 | I71: ='Historical FS'!I28 -> 3859 | J71: ='Historical FS'!J28 -> 7417 | ... L71: ='Historical FS'!L28 -> 5345 | M71: =M72*M7 -> 6871.7211 | N71: =N72*N7 -> 7410.6243 | O71: =O72*O7 -> 7991.79 | P71: =P72*P7 -> 8618.5327 | Q71: =Q72*Q7 -> 9294.4266
B72: % of sales | C72: =C71/C7 -> 0.05164533 | D72: =D71/D7 -> 0.064884325 | E72: =E71/E7 -> 0.039011312 | F72: =F71/F7 -> 0.034156894 | G72: =G71/G7 -> 0.02871543 | H72: =H71/H7 -> 0.031017895 | I72: =I71/I7 -> 0.031117454 | J72: =J71/J7 -> 0.057526002 | ... L72: =L71/L7 -> 0.035916113 | M72: =AVERAGE($J72:$L72) -> 0.042817162 | N72: =AVERAGE($J72:$L72) -> 0.042817162 | O72: =AVERAGE($J72:$L72) -> 0.042817162 | P72: =AVERAGE($J72:$L72) -> 0.042817162 | Q72: =AVERAGE($J72:$L72) -> 0.042817162
B75: Other Assets | C75: ='Historical FS'!C62 -> 14228 | D75: ='Historical FS'!D62 -> 17193 | E75: ='Historical FS'!E62 -> 18316 | F75: ='Historical FS'!F62 -> 17554 | G75: ='Historical FS'!G62 -> 18624 | H75: ='Historical FS'!H62 -> 22049 | I75: ='Historical FS'!I62 -> 27259 | J75: ='Historical FS'!J62 -> 23596 | ... L75: ='Historical FS'!L62 -> 28643 | M75: =M76*M7 -> 30102.958 | N75: =N76*N7 -> 32463.732 | O75: =O76*O7 -> 35009.646 | P75: =P76*P7 -> 37755.218 | Q75: =Q76*Q7 -> 40716.107
B76: % of sales | C76: =C75/C7 -> 0.23997706 | D76: =D75/D7 -> 0.27757059 | E76: =E75/E7 -> 0.25053688 | F76: =F75/F7 -> 0.22207041 | G76: =G75/G7 -> 0.21677996 | H76: =H75/H7 -> 0.212132 | I76: =I75/I7 -> 0.21980583 | J76: =J75/J7 -> 0.18300978 | ... L76: =L75/L7 -> 0.1924687 | M76: =AVERAGE($J76:$L76) -> 0.1875692 | N76: =AVERAGE($J76:$L76) -> 0.1875692 | O76: =AVERAGE($J76:$L76) -> 0.1875692 | P76: =AVERAGE($J76:$L76) -> 0.1875692 | Q76: =AVERAGE($J76:$L76) -> 0.1875692
B78: Other Liabilities ( total) | C78: ='Historical FS'!C48 -> 11868 | D78: ='Historical FS'!D48 -> 11870 | E78: ='Historical FS'!E48 -> 15678 | F78: ='Historical FS'!F48 -> 15086 | G78: ='Historical FS'!G48 -> 18043 | H78: ='Historical FS'!H48 -> 25454 | I78: ='Historical FS'!I48 -> 28547 | J78: ='Historical FS'!J48 -> 30008 | ... L78: ='Historical FS'!L48 -> 41078 | M78: =M80+M82 -> 40518.196 | N78: =N80+N82 -> 43741.634 | O78: =O80+O82 -> 47222.063 | P78: =P80+P82 -> 50980.022 | Q78: =Q80+Q82 -> 55037.695
B80: Trade payables | C80: =C99 -> 269 | D80: =D99 -> 738 | E80: =E99 -> 1604 | F80: =F99 -> 1529 | G80: =G99 -> 1562 | H80: =H99 -> 2669 | I80: =I99 -> 2426 | J80: =J99 -> 2493 | ... Q80: =Q99 -> 4964.9396
B82: Other liabilities | C82: =C78-C80 -> 11599 | D82: =D78-D80 -> 11132 | E82: =E78-E80 -> 14074 | F82: =F78-F80 -> 13557 | G82: =G78-G80 -> 16481 | H82: =H78-H80 -> 22785 | I82: =I78-I80 -> 26121 | J82: =J78-J80 -> 27515 | ... L82: =L78-L80 -> 37539 | M82: =M83*M7 -> 37020.682 | N82: =N83*N7 -> 39923.967 | O82: =O83*O7 -> 43054.937 | P82: =P83*P7 -> 46431.447 | Q82: =Q83*Q7 -> 50072.755
B83: % of sales | C83: =C82/C7 -> 0.19563494 | D83: =D82/D7 -> 0.17971941 | E83: =E82/E7 -> 0.19251234 | F83: =F82/F7 -> 0.17150556 | G83: =G82/G7 -> 0.19183583 | H83: =H82/H7 -> 0.21921301 | I83: =I82/I7 -> 0.21062945 | J83: =J82/J7 -> 0.21340541 | ... L83: =L82/L7 -> 0.25224602 | M83: =AVERAGE($J83:$L83) -> 0.230673 | N83: =AVERAGE($J83:$L83) -> 0.230673 | O83: =AVERAGE($J83:$L83) -> 0.230673 | P83: =AVERAGE($J83:$L83) -> 0.230673 | Q83: =AVERAGE($J83:$L83) -> 0.230673
B85: Dividend | C85: ='Historical FS'!C39 -> 5912.2 | D85: ='Historical FS'!D39 -> 9500.4 | E85: ='Historical FS'!E39 -> 9365.4 | F85: ='Historical FS'!F39 -> 7451.5 | G85: ='Historical FS'!G39 -> 11502 | H85: ='Historical FS'!H39 -> 13038.6 | I85: ='Historical FS'!I39 -> 14103.2 | J85: ='Historical FS'!J39 -> 19090 | ... L85: ='Historical FS'!L39 -> 19459.2
B86: Divident ratio | C86: ='Historical FS'!C40 -> 0.42786221 | D86: ='Historical FS'!D40 -> 0.58807799 | E86: ='Historical FS'!E40 -> 0.63701537 | F86: ='Historical FS'!F40 -> 0.47941195 | G86: ='Historical FS'!G40 -> 0.63730053 | H86: ='Historical FS'!H40 -> 0.6140146 | I86: ='Historical FS'!I40 -> 0.60611999 | J86: ='Historical FS'!J40 -> 0.70096203 | ... L86: ='Historical FS'!L40 -> 0.66616001 | M86: =AVERAGE($J86:$L86) -> 0.68846705 | N86: =AVERAGE($J86:$L86) -> 0.68846705 | O86: =AVERAGE($J86:$L86) -> 0.68846705 | P86: =AVERAGE($J86:$L86) -> 0.68846705 | Q86: =AVERAGE($J86:$L86) -> 0.68846705
B87: Retention Ratio | C87: =1-C86 -> 0.57213779 | D87: =1-D86 -> 0.41192201 | E87: =1-E86 -> 0.36298463 | F87: =1-F86 -> 0.52058805 | G87: =1-G86 -> 0.36269947 | H87: =1-H86 -> 0.3859854 | I87: =1-I86 -> 0.39388001 | J87: =1-J86 -> 0.29903797 | ... Q87: =1-Q86 -> 0.31153295
B89: Tax | M89: 0.2517 | N89: 0.2517 | O89: 0.2517 | P89: 0.2517 | Q89: 0.2517
A93: # | B93: Working Capital
B95: Trade recievbles | C95: ='Historical FS'!C59 -> 10960 | D95: ='Historical FS'!D59 -> 12151 | E95: ='Historical FS'!E59 -> 13370 | F95: ='Historical FS'!F59 -> 15459 | G95: ='Historical FS'!G59 -> 16394 | H95: ='Historical FS'!H59 -> 18966 | I95: ='Historical FS'!I59 -> 20773 | J95: ='Historical FS'!J59 -> 25152 | ... L95: ='Historical FS'!L59 -> 30337 | M95: =M7*M96/360 -> 31686.117 | N95: =N7*N96/360 -> 34171.048 | O95: =O7*O96/360 -> 36850.854 | P95: =P7*P96/360 -> 39740.82 | Q95: =Q7*Q96/360 -> 42857.427
B96: Debtor days | C96: ='Ratio Analysis'!C38 -> 66.548601 | D96: ='Ratio Analysis'!D38 -> 70.621398 | E96: ='Ratio Analysis'!E38 -> 65.837745 | F96: ='Ratio Analysis'!F38 -> 70.40419 | G96: ='Ratio Analysis'!G38 -> 68.69634 | H96: ='Ratio Analysis'!H38 -> 65.689436 | I96: ='Ratio Analysis'!I38 -> 60.301901 | J96: ='Ratio Analysis'!J38 -> 70.228103 | ... L96: ='Ratio Analysis'!L38 -> 73.386597 | M96: =AVERAGE($J96:$L96) -> 71.076147 | N96: =AVERAGE($J96:$L96) -> 71.076147 | O96: =AVERAGE($J96:$L96) -> 71.076147 | P96: =AVERAGE($J96:$L96) -> 71.076147 | Q96: =AVERAGE($J96:$L96) -> 71.076147
B99: Trade payavbles | C99: ='Balance sheet'!E19 -> 269 | D99: ='Balance sheet'!F19 -> 738 | E99: ='Balance sheet'!G19 -> 1604 | F99: ='Balance sheet'!H19 -> 1529 | G99: ='Balance sheet'!I19 -> 1562 | H99: ='Balance sheet'!J19 -> 2669 | I99: ='Balance sheet'!K19 -> 2426 | J99: ='Balance sheet'!L19 -> 2493 | ... L99: ='Balance sheet'!N19 -> 3539 | M99: =M43*M100/360 -> 3497.5135 | N99: =N43*N100/360 -> 3817.667 | O99: =O43*O100/360 -> 4167.1265 | P99: =P43*P100/360 -> 4548.5746 | Q99: =Q43*Q100/360 -> 4964.9396
B100: Creditor Days | C100: =360*C99/C43 -> 13.215066 | D100: =360*D99/D43 -> 33.844586 | E100: =360*E99/E43 -> 54.749218 | F100: =360*F99/F43 -> 47.673653 | G100: =360*G99/G43 -> 43.996557 | H100: =360*H99/H43 -> 47.469987 | I100: =360*I99/I43 -> 34.340988 | J100: =360*J99/J43 -> 33.642464 | ... L100: =360*L99/L43 -> 38.574543 | M100: =AVERAGE($J100:$L100) -> 34.925367 | N100: =AVERAGE($J100:$L100) -> 34.925367 | O100: =AVERAGE($J100:$L100) -> 34.925367 | P100: =AVERAGE($J100:$L100) -> 34.925367 | Q100: =AVERAGE($J100:$L100) -> 34.925367
B102: Loans and Advances | C102: ='Historical FS'!C61 -> 715 | D102: ='Historical FS'!D61 -> 760 | E102: ='Historical FS'!E61 -> 1304 | F102: ='Historical FS'!F61 -> 1069 | G102: ='Historical FS'!G61 -> 1138 | H102: ='Historical FS'!H61 -> 1576 | I102: ='Historical FS'!I61 -> 2124 | J102: ='Historical FS'!J61 -> 8748 | ... L102: ='Historical FS'!L61 -> 5571 | M102: =M103*M7 -> 6253.8823 | N102: =N103*N7 -> 6744.3325 | O102: =O103*O7 -> 7273.2454 | P102: =P103*P7 -> 7843.6374 | Q102: =Q103*Q7 -> 8458.7614
B103: % of sales | C103: =C102/C7 -> 0.012059573 | D103: =D102/D7 -> 0.012269741 | E103: =E102/E7 -> 0.017836869 | F103: =F102/F7 -> 0.0135236 | G103: =G102/G7 -> 0.013246112 | H103: =H102/H7 -> 0.015162594 | I103: =I102/I7 -> 0.017127099 | J103: =J102/J7 -> 0.067849193 | ... L103: =L102/L7 -> 0.037434736 | M103: =AVERAGE($K103:$L103) -> 0.038967456 | N103: =AVERAGE($K103:$L103) -> 0.038967456 | O103: =AVERAGE($K103:$L103) -> 0.038967456 | P103: =AVERAGE($K103:$L103) -> 0.038967456 | Q103: =AVERAGE($K103:$L103) -> 0.038967456

Sheet Forecasted FS
B2: ='DATA Sheet'!B1&" Forecasted FS" -> INFOSYS LTD Forecasted FS
B3: Years (As on March) | C3: 2027 | D3: =C3+1 -> 2028 | E3: =D3+1 -> 2029 | F3: =E3+1 -> 2030 | G3: =F3+1 -> 2031
A5: # | B5: Income Statement | I5: Scenario | J5: =DASHBOARD!D2 -> Base | L5: Pessmistic | M5: Base | N5: Optmistic
B7: Sales | C7: ='Forecast Drivers'!M7 -> 160489.88 | D7: ='Forecast Drivers'!N7 -> 173076.03 | E7: ='Forecast Drivers'!O7 -> 186649.22 | F7: ='Forecast Drivers'!P7 -> 201286.87 | G7: ='Forecast Drivers'!Q7 -> 217072.46
B9: COGS | C9: ='Forecast Drivers'!M32 -> 113755.42 | D9: ='Forecast Drivers'!N32 -> 121772.55 | E9: ='Forecast Drivers'!O32 -> 130378.12 | F9: ='Forecast Drivers'!P32 -> 139617.15 | G9: ='Forecast Drivers'!Q32 -> 149538.27
B11: Gross profit | C11: =C7-C9 -> 46734.458 | D11: =D7-D9 -> 51303.474 | E11: =E7-E9 -> 56271.105 | F11: =F7-F9 -> 61669.725 | G11: =G7-G9 -> 67534.189
B12: Gross margin | C12: =C11/C7 -> 0.29119879 | D12: =D11/D7 -> 0.29642161 | E12: =E11/E7 -> 0.30148052 | F12: =F11/F7 -> 0.30637728 | G12: =G11/G7 -> 0.31111358
B15: SG&A | C15: ='Forecast Drivers'!M47 -> 6694.3954 | D15: ='Forecast Drivers'!N47 -> 7219.3921 | E15: ='Forecast Drivers'!O47 -> 7785.5607 | F15: ='Forecast Drivers'!P47 -> 8396.1302 | G15: ='Forecast Drivers'!Q47 -> 9054.5826
B17: EBITDA | C17: =C11-C15 -> 40040.063 | D17: =D11-D15 -> 44084.082 | E17: =E11-E15 -> 48485.545 | F17: =F11-F15 -> 53273.595 | G17: =G11-G15 -> 58479.607
B18: % of sales | C18: =C17/C7 -> 0.24948653 | D18: =D17/D7 -> 0.25470935 | E18: =E17/E7 -> 0.25976826 | F18: =F17/F7 -> 0.26466502 | G18: =G17/G7 -> 0.26940132
B20: Depreciation | C20: ='Forecast Drivers'!M56 -> 3107.8389 | D20: ='Forecast Drivers'!N56 -> 3351.566 | E20: ='Forecast Drivers'!O56 -> 3614.4069 | F20: ='Forecast Drivers'!P56 -> 3897.8606 | G20: ='Forecast Drivers'!Q56 -> 4203.5438
B23: Interest | C23: ='Forecast Drivers'!M65 -> 234.91537 | D23: ='Forecast Drivers'!N65 -> 234.91537 | E23: ='Forecast Drivers'!O65 -> 234.91537 | F23: ='Forecast Drivers'!P65 -> 234.91537 | G23: ='Forecast Drivers'!Q65 -> 234.91537
B26: Other Income | C26: ='Forecast Drivers'!M71 -> 6871.7211 | D26: ='Forecast Drivers'!N71 -> 7410.6243 | E26: ='Forecast Drivers'!O71 -> 7991.79 | F26: ='Forecast Drivers'!P71 -> 8618.5327 | G26: ='Forecast Drivers'!Q71 -> 9294.4266
B28: PBT | C28: =C17-C20-C23+C26 -> 43569.029 | D28: =D17-D20-D23+D26 -> 47908.225 | E28: =E17-E20-E23+E26 -> 52628.012 | F28: =F17-F20-F23+F26 -> 57759.351 | G28: =G17-G20-G23+G26 -> 63335.574
B30: Tax | C30: =C28*'Forecast Drivers'!M89 -> 10966.325 | D30: =D28*'Forecast Drivers'!N89 -> 12058.5 | E30: =E28*'Forecast Drivers'!O89 -> 13246.471 | F30: =F28*'Forecast Drivers'!P89 -> 14538.029 | G30: =G28*'Forecast Drivers'!Q89 -> 15941.564
B32: Net profit | C32: =C28-C30 -> 32602.705 | D32: =D28-D30 -> 35849.725 | E32: =E28-E30 -> 39381.542 | F32: =F28-F30 -> 43221.323 | G32: =G28-G30 -> 47394.01
B33: Net Margin | C33: =C32/C7 -> 0.20314493 | D33: =D32/D7 -> 0.20713281 | E33: =E32/E7 -> 0.21099226 | F33: =F32/F7 -> 0.21472499 | G33: =G32/G7 -> 0.21833267
A37: # | B37: Balance Sheet
B39: Equity Share Capital | C39: ='Historical FS'!L45 -> 2027 | D39: =C39 -> 2027 | E39: =D39 -> 2027 | F39: =E39 -> 2027 | G39: =F39 -> 2027
B40: Reserves | C40: ='Historical FS'!L46+C32*'Forecast Drivers'!M87 -> 89003.817 | D40: =C40+D32*'Forecast Drivers'!N87 -> 100172.19 | E40: =D40+E32*'Forecast Drivers'!O87 -> 112440.84 | F40: =E40+F32*'Forecast Drivers'!P87 -> 125905.7 | G40: =F40+G32*'Forecast Drivers'!Q87 -> 140670.5
B41: Borrowings | C41: ='Forecast Drivers'!M62 -> 3658 | D41: ='Forecast Drivers'!N62 -> 3658 | E41: ='Forecast Drivers'!O62 -> 3658 | F41: ='Forecast Drivers'!P62 -> 3658 | G41: ='Forecast Drivers'!Q62 -> 3658
B42: Other Liabilities | C42: ='Forecast Drivers'!M78 -> 40518.196 | D42: ='Forecast Drivers'!N78 -> 43741.634 | E42: ='Forecast Drivers'!O78 -> 47222.063 | F42: ='Forecast Drivers'!P78 -> 50980.022 | G42: ='Forecast Drivers'!Q78 -> 55037.695
B44: Total Liablities | C44: =SUM(C39:C42) -> 135207.01 | D44: =SUM(D39:D42) -> 149598.82 | E44: =SUM(E39:E42) -> 165347.9 | F44: =SUM(F39:F42) -> 182570.72 | G44: =SUM(G39:G42) -> 201393.19
B47: Fixed Assets | C47: ='Forecast Drivers'!M53 -> 16059.723 | D47: ='Forecast Drivers'!N53 -> 17319.18 | E47: ='Forecast Drivers'!O53 -> 18677.408 | F47: ='Forecast Drivers'!P53 -> 20142.152 | G47: ='Forecast Drivers'!Q53 -> 21721.766
B48: Capital Work in Progress | C48: ='Historical FS'!L54 -> 512 | D48: =C48 -> 512 | E48: =D48 -> 512 | F48: =E48 -> 512 | G48: =F48 -> 512
B49: Investments | C49: ='Historical FS'!L55 -> 38075 | D49: =C49 -> 38075 | E49: =D49 -> 38075 | F49: =E49 -> 38075 | G49: =F49 -> 38075
B51: Total Non Current Assets | C51: =SUM(C47:C49) -> 54646.723 | D51: =SUM(D47:D49) -> 55906.18 | E51: =SUM(E47:E49) -> 57264.408 | F51: =SUM(F47:F49) -> 58729.152 | G51: =SUM(G47:G49) -> 60308.766
B53: Trade receivables | C53: ='Forecast Drivers'!M95 -> 31686.117 | D53: ='Forecast Drivers'!N95 -> 34171.048 | E53: ='Forecast Drivers'!O95 -> 36850.854 | F53: ='Forecast Drivers'!P95 -> 39740.82 | G53: ='Forecast Drivers'!Q95 -> 42857.427
B54: Cash Equivalents | C54: =C87 -> 12517.331 | D54: =D87 -> 20313.529 | E54: =E87 -> 28949.746 | F54: =F87 -> 38501.896 | G54: =G87 -> 49052.13
B55: Loans and Advances | C55: ='Forecast Drivers'!M102 -> 6253.8823 | D55: ='Forecast Drivers'!N102 -> 6744.3325 | E55: ='Forecast Drivers'!O102 -> 7273.2454 | F55: ='Forecast Drivers'!P102 -> 7843.6374 | G55: ='Forecast Drivers'!Q102 -> 8458.7614
B56: Other asset items | C56: ='Forecast Drivers'!M75 -> 30102.958 | D56: ='Forecast Drivers'!N75 -> 32463.732 | E56: ='Forecast Drivers'!O75 -> 35009.646 | F56: ='Forecast Drivers'!P75 -> 37755.218 | G56: ='Forecast Drivers'!Q75 -> 40716.107
B58: Total Current Assets | C58: =SUM(C53:C56) -> 80560.289 | D58: =SUM(D53:D56) -> 93692.641 | E58: =SUM(E53:E56) -> 108083.49 | F58: =SUM(F53:F56) -> 123841.57 | G58: =SUM(G53:G56) -> 141084.43
B60: Total assets | C60: =C58+C51 -> 135207.01 | D60: =D58+D51 -> 149598.82 | E60: =E58+E51 -> 165347.9 | F60: =F58+F51 -> 182570.72 | G60: =G58+G51 -> 201393.19
B62: Check | C62: =C60=C44 -> TRUE | D62: =D60=D44 -> TRUE | E62: =E60=E44 -> TRUE | F62: =F60=F44 -> TRUE | G62: =G60=G44 -> TRUE
A64: # | B64: Cashflow Statement
B66: Operating Activities
B68: Net profit | C68: =C32 -> 32602.705 | D68: =D32 -> 35849.725 | E68: =E32 -> 39381.542 | F68: =F32 -> 43221.323 | G68: =G32 -> 47394.01
B69: Depreciation | C69: =C20 -> 3107.8389 | D69: =D20 -> 3351.566 | E69: =E20 -> 3614.4069 | F69: =F20 -> 3897.8606 | G69: =G20 -> 4203.5438
B70: Changes In the Working Capital | C70: =-((C56+C55+C53-C42)-('Historical FS'!L62+'Historical FS'!L61+'Historical FS'!L59-'Historical FS'!L48)) -> -4051.7623 | D70: =-((D56+D55+D53-D42)-(C56+C55+C53-C42)) -> -2112.7162 | E70: =-((E56+E55+E53-E42)-(D56+D55+D53-D42)) -> -2274.2039 | F70: =-((F56+F55+F53-F42)-(E56+E55+E53-E42)) -> -2447.9716 | G70: =-((G56+G55+G53-G42)-(F56+F55+F53-F42)) -> -2634.9473
B71: Direct tax
B72: Cashflow from Operations | C72: =SUM(C68:C70) -> 31658.781 | D72: =SUM(D68:D70) -> 37088.574 | E72: =SUM(E68:E70) -> 40721.745 | F72: =SUM(F68:F70) -> 44671.212 | G72: =SUM(G68:G70) -> 48962.607
B74: Investing Activities
B75: New Capex | C75: =-(C47-'Historical FS'!L53+'Forecasted FS'!C20) -> -5331.5622 | D75: =-(D47-C47+D20) -> -4611.0227 | E75: =-(E47-D47+E20) -> -4972.6344 | F75: =-(F47-E47+F20) -> -5362.6048 | G75: =-(G47-F47+G20) -> -5783.1581
B77: Cashflow from Investing Activities | C77: =C75 -> -5331.5622 | D77: =D75 -> -4611.0227 | E77: =E75 -> -4972.6344 | F77: =F75 -> -5362.6048 | G77: =G75 -> -5783.1581
B79: Financing Activities
B80: New borrowings | C80: =C41-'Historical FS'!L47 -> -91 | D80: =D41-C41 -> 0 | E80: =E41-D41 -> 0 | F80: =F41-E41 -> 0 | G80: =G41-F41 -> 0
B81: Dividends paid | C81: =-'Forecast Drivers'!M86*'Forecasted FS'!C32 -> -22445.888 | D81: =-'Forecast Drivers'!N86*'Forecasted FS'!D32 -> -24681.354 | E81: =-'Forecast Drivers'!O86*'Forecasted FS'!E32 -> -27112.894 | F81: =-'Forecast Drivers'!P86*'Forecasted FS'!F32 -> -29756.456 | G81: =-'Forecast Drivers'!Q86*'Forecasted FS'!G32 -> -32629.214
B83: Cashflow from Financing Activities | C83: =SUM(C80:C81) -> -22536.888 | D83: =SUM(D80:D81) -> -24681.354 | E83: =SUM(E80:E81) -> -27112.894 | F83: =SUM(F80:F81) -> -29756.456 | G83: =SUM(G80:G81) -> -32629.214
B85: Net Change in Cash | C85: =C83+C77+C72 -> 3790.3313 | D85: =D83+D77+D72 -> 7796.1977 | E85: =E83+E77+E72 -> 8636.2166 | F85: =F83+F77+F72 -> 9552.1505 | G85: =G83+G77+G72 -> 10550.234
B86: Opening Cash | C86: ='Historical FS'!L60 -> 8727 | D86: =C87 -> 12517.331 | E86: =D87 -> 20313.529 | F86: =E87 -> 28949.746 | G86: =F87 -> 38501.896
B87: Closing Cash | C87: =SUM(C85:C86) -> 12517.331 | D87: =SUM(D85:D86) -> 20313.529 | E87: =SUM(E85:E86) -> 28949.746 | F87: =SUM(F85:F86) -> 38501.896 | G87: =SUM(G85:G86) -> 49052.13

Sheet Comprables
A1: 0

Sheet EV-EBITDA
B3: Comparables
B4: Particulars | C4: Infosys | D4: TCS | E4: HCL | F4: Wipro
B6: Market CAP | C6: ='DATA Sheet'!B9 -> 464241.67 | D6: 867347 | E6: 355979 | F6: 183298
B7: Debt | C7: ='Historical FS'!L47 -> 3749 | D7: 11283 | E7: 988 | F7: 20291
B8: Cash | C8: ='Historical FS'!L60 -> 8727 | D8: 12908 | E8: 3794 | F8: 10556
B9: EV | C9: =C6+C7-C8 -> 459263.67 | D9: =D6+D7-D8 -> 865722 | E9: =E6+E7-E8 -> 353173 | F9: =F6+F7-F8 -> 193033
B12: EBITDA | C12: ='Historical FS'!L18 -> 36013 | D12: 74079 | E12: 17059 | F12: 18211
B14: EV/EBITDA | C14: =C9/C12 -> 12.752719 | D14: =D9/D12 -> 11.68647 | E14: =E9/E12 -> 20.703031 | F14: =F9/F12 -> 10.599802

Sheet DCF Valuation >>

Sheet DCF
A3: # | B3: ='DATA Sheet'!B1&" DCF Valuation" -> INFOSYS LTD DCF Valuation
B4: Years (As on March) | C4: 2027 | D4: =C4+1 -> 2028 | E4: =D4+1 -> 2029 | F4: =E4+1 -> 2030 | G4: =F4+1 -> 2031 | I4: Exit Multiple
B5: NOPAT | C5: =('Forecasted FS'!C17-'Forecasted FS'!C20)*(1-'Forecast Drivers'!M89) -> 27636.383 | D5: =('Forecasted FS'!D17-'Forecasted FS'!D20)*(1-'Forecast Drivers'!N89) -> 30480.142 | E5: =('Forecasted FS'!E17-'Forecasted FS'!E20)*(1-'Forecast Drivers'!O89) -> 33577.072 | F5: =('Forecasted FS'!F17-'Forecasted FS'!F20)*(1-'Forecast Drivers'!P89) -> 36947.862 | G5: =('Forecasted FS'!G17-'Forecasted FS'!G20)*(1-'Forecast Drivers'!Q89) -> 40614.778 | I5: FCF FY31 | J5: =G13 -> 36400.216
A6: + | B6: Depreciation | C6: ='Forecasted FS'!C20 -> 3107.8389 | D6: ='Forecasted FS'!D20 -> 3351.566 | E6: ='Forecasted FS'!E20 -> 3614.4069 | F6: ='Forecasted FS'!F20 -> 3897.8606 | G6: ='Forecasted FS'!G20 -> 4203.5438 | I6: GDp growth | J6: =7%+Scenarios!$H$6 -> 0.07
A7: - | B7: CAPEX | C7: ='Forecasted FS'!C75 -> -5331.5622 | D7: ='Forecasted FS'!D75 -> -4611.0227 | E7: ='Forecasted FS'!E75 -> -4972.6344 | F7: ='Forecasted FS'!F75 -> -5362.6048 | G7: ='Forecasted FS'!G75 -> -5783.1581 | I7: WACC | J7: =WACC!I7 -> 0.11798466
A8: - | B8: Changes in WC | C8: ='Forecasted FS'!C70 -> -4051.7623 | D8: ='Forecasted FS'!D70 -> -2112.7162 | E8: ='Forecasted FS'!E70 -> -2274.2039 | F8: ='Forecasted FS'!F70 -> -2447.9716 | G8: ='Forecasted FS'!G70 -> -2634.9473 | I8: Terminal Value | J8: =$J$5*(1+$J$6)/($J$7-$J$6) -> 811680.96
B10: Free cash Flows | C10: =SUM(C5:C8) -> 21360.897 | D10: =SUM(D5:D8) -> 27107.969 | E10: =SUM(E5:E8) -> 29944.641 | F10: =SUM(F5:F8) -> 33035.146 | G10: =SUM(G5:G8) -> 36400.216
B13: FCF | C13: =C10 -> 21360.897 | D13: =D10 -> 27107.969 | E13: =E10 -> 29944.641 | F13: =F10 -> 33035.146 | G13: =G10 -> 36400.216
B14: Terminal Value | C14: 0 | D14: 0 | E14: 0 | F14: 0 | G14: 0
B15: Cash inflow | C15: =SUM(C13:C14) -> 21360.897 | D15: =SUM(D13:D14) -> 27107.969 | E15: =SUM(E13:E14) -> 29944.641 | F15: =SUM(F13:F14) -> 33035.146 | G15: =SUM(G13:G14) -> 36400.216
A19: # | B19: D.F | C19: =WACC!I7 -> 0.11798466
E20: EV | F20: =C23 -> 568947.71 | H20: Equity value | I20: =F23 -> 563969.71
B21: PV of Cash Inflow | C21: =NPV(C19,C13,D13,E13,F13,G13) -> 104211.9 | E21: Cash | F21: ='Historical FS'!L60 -> 8727 | H21: No of shares | I21: ='DATA Sheet'!B6 -> 405.80566
B22: PV of terminal Value | C22: =J8/(1+C19)^5 -> 464735.81 | E22: Debt | F22: ='Historical FS'!L47 -> 3749 | H22: Equity value per share | I22: =I20/I21 -> 1389.7532
B23: Enterprise value | C23: =SUM(C21:C22) -> 568947.71 | E23: Equity | F23: =F20+F22-F21 -> 563969.71
A27: # | B27: Senstivity Analysis
B28: =I22 -> 1389.7532 | C28: =D28-0.01 -> 0.06 | D28: =J6 -> 0.07 | E28: =D28+0.01 -> 0.08 | F28: =E28+0.01 -> 0.09 | G28: =F28+0.01 -> 0.1
B29: =B30-1% -> 0.10798466 | C29: =((NPV($B29,$C$13,$D$13,$E$13,$F$13,$G$13)+($J$5*(1+C$28)/($J$7-C$28))/(1+$B29)^5)+($F$21-$F$22))/$I$21 -> 1258.1694 | D29: =((NPV($B29,$C$13,$D$13,$E$13,$F$13,$G$13)+($J$5*(1+D$28)/($J$7-D$28))/(1+$B29)^5)+($F$21-$F$22))/$I$21 -> 1474.0121 | E29: =((NPV($B29,$C$13,$D$13,$E$13,$F$13,$G$13)+($J$5*(1+E$28)/($J$7-E$28))/(1+$B29)^5)+($F$21-$F$22))/$I$21 -> 1803.5023 | F29: =((NPV($B29,$C$13,$D$13,$E$13,$F$13,$G$13)+($J$5*(1+F$28)/($J$7-F$28))/(1+$B29)^5)+($F$21-$F$22))/$I$21 -> 2368.4715 | G29: =((NPV($B29,$C$13,$D$13,$E$13,$F$13,$G$13)+($J$5*(1+G$28)/($J$7-G$28))/(1+$B29)^5)+($F$21-$F$22))/$I$21 -> 3561.7199
B30: =C19 -> 0.11798466 | C30: =((NPV($B30,$C$13,$D$13,$E$13,$F$13,$G$13)+($J$5*(1+C$28)/($J$7-C$28))/(1+$B30)^5)+($F$21-$F$22))/$I$21 -> 1207.9264 | D30: =((NPV($B30,$C$13,$D$13,$E$13,$F$13,$G$13)+($J$5*(1+D$28)/($J$7-D$28))/(1+$B30)^5)+($F$21-$F$22))/$I$21 -> 1414.2871 | E30: =((NPV($B30,$C$13,$D$13,$E$13,$F$13,$G$13)+($J$5*(1+E$28)/($J$7-E$28))/(1+$B30)^5)+($F$21-$F$22))/$I$21 -> 1729.3026 | F30: =((NPV($B30,$C$13,$D$13,$E$13,$F$13,$G$13)+($J$5*(1+F$28)/($J$7-F$28))/(1+$B30)^5)+($F$21-$F$22))/$I$21 -> 2269.4525 | G30: =((NPV($B30,$C$13,$D$13,$E$13,$F$13,$G$13)+($J$5*(1+G$28)/($J$7-G$28))/(1+$B30)^5)+($F$21-$F$22))/$I$21 -> 3410.2811
B31: =B30+1% -> 0.12798466 | C31: =((NPV($B31,$C$13,$D$13,$E$13,$F$13,$G$13)+($J$5*(1+C$28)/($J$7-C$28))/(1+$B31)^5)+($F$21-$F$22))/$I$21 -> 1160.2284 | D31: =((NPV($B31,$C$13,$D$13,$E$13,$F$13,$G$13)+($J$5*(1+D$28)/($J$7-D$28))/(1+$B31)^5)+($F$21-$F$22))/$I$21 -> 1357.6025 | E31: =((NPV($B31,$C$13,$D$13,$E$13,$F$13,$G$13)+($J$5*(1+E$28)/($J$7-E$28))/(1+$B31)^5)+($F$21-$F$22))/$I$21 -> 1658.8998 | F31: =((NPV($B31,$C$13,$D$13,$E$13,$F$13,$G$13)+($J$5*(1+F$28)/($J$7-F$28))/(1+$B31)^5)+($F$21-$F$22))/$I$21 -> 2175.5274 | G31: =((NPV($B31,$C$13,$D$13,$E$13,$F$13,$G$13)+($J$5*(1+G$28)/($J$7-G$28))/(1+$B31)^5)+($F$21-$F$22))/$I$21 -> 3266.6753
B32: =B31+1% -> 0.13798466 | C32: =((NPV($B32,$C$13,$D$13,$E$13,$F$13,$G$13)+($J$5*(1+C$28)/($J$7-C$28))/(1+$B32)^5)+($F$21-$F$22))/$I$21 -> 1114.9239 | D32: =((NPV($B32,$C$13,$D$13,$E$13,$F$13,$G$13)+($J$5*(1+D$28)/($J$7-D$28))/(1+$B32)^5)+($F$21-$F$22))/$I$21 -> 1303.7771 | E32: =((NPV($B32,$C$13,$D$13,$E$13,$F$13,$G$13)+($J$5*(1+E$28)/($J$7-E$28))/(1+$B32)^5)+($F$21-$F$22))/$I$21 -> 1592.0667 | F32: =((NPV($B32,$C$13,$D$13,$E$13,$F$13,$G$13)+($J$5*(1+F$28)/($J$7-F$28))/(1+$B32)^5)+($F$21-$F$22))/$I$21 -> 2086.3905 | G32: =((NPV($B32,$C$13,$D$13,$E$13,$F$13,$G$13)+($J$5*(1+G$28)/($J$7-G$28))/(1+$B32)^5)+($F$21-$F$22))/$I$21 -> 3130.4316
B33: =B32+1% -> 0.14798466 | C33: =((NPV($B33,$C$13,$D$13,$E$13,$F$13,$G$13)+($J$5*(1+C$28)/($J$7-C$28))/(1+$B33)^5)+($F$21-$F$22))/$I$21 -> 1071.872 | D33: =((NPV($B33,$C$13,$D$13,$E$13,$F$13,$G$13)+($J$5*(1+D$28)/($J$7-D$28))/(1+$B33)^5)+($F$21-$F$22))/$I$21 -> 1252.6417 | E33: =((NPV($B33,$C$13,$D$13,$E$13,$F$13,$G$13)+($J$5*(1+E$28)/($J$7-E$28))/(1+$B33)^5)+($F$21-$F$22))/$I$21 -> 1528.5919 | F33: =((NPV($B33,$C$13,$D$13,$E$13,$F$13,$G$13)+($J$5*(1+F$28)/($J$7-F$28))/(1+$B33)^5)+($F$21-$F$22))/$I$21 -> 2001.7575 | G33: =((NPV($B33,$C$13,$D$13,$E$13,$F$13,$G$13)+($J$5*(1+G$28)/($J$7-G$28))/(1+$B33)^5)+($F$21-$F$22))/$I$21 -> 3001.1111

Sheet WACC
E3: ='DATA Sheet'!B1&" DCF Valuation" -> INFOSYS LTD DCF Valuation
E4: Years (As on March) | F4: Amt | G4: Weight | H4: Cost | I4: Weighted avg
E5: Equity | F5: ='DATA Sheet'!B9 -> 464241.67 | G5: =F5/F7 -> 0.99198916 | H5: =CAPM!C9 -> 0.11860138 | I5: =G5*H5 -> 0.11765128
E6: Debt | F6: ='Historical FS'!L47 -> 3749 | G6: =F6/F7 -> 0.0080108435 | H6: ='Forecast Drivers'!L66*(1-'Historical FS'!L35) -> 0.041615122 | I6: =G6*H6 -> 0.00033337223
E7: Total | F7: =SUM(F5:F6) -> 467990.67 | I7: =SUM(I5:I6) -> 0.11798466

Sheet CAPM
B3: ='DATA Sheet'!B1&" CAPM" -> INFOSYS LTD CAPM
B5: Risk Free return | C5: 0.07
B6: Market return | C6: 0.12
B7: Beta | C7: =BETA!K6 -> 0.97202762
B9: Cost of equity | C9: =C5+C7*(C6-C5) -> 0.11860138

Sheet BETA
B3: Nifty returns | F3: Infosys Returns
B4: Date | C4: Close | D4: Return | F4: Date | G4: Close | H4: Return
B5: 44438 | C5: 16931.05 | F5: 44438 | G5: 1698.05
B6: 44439 | C6: 17132.2 | D6: =C6/C5-1 -> 0.011880539 | F6: 44439 | G6: 1706.45 | H6: =G6/G5-1 -> 0.0049468508 | J6: Beta | K6: =SLOPE(H6:H1245,D6:D1245) -> 0.97202762
B7: 44440 | C7: 17076.25 | D7: =C7/C6-1 -> -0.0032657802 | F7: 44440 | G7: 1677.75 | H7: =G7/G6-1 -> -0.016818541
B8: 44441 | C8: 17234.15 | D8: =C8/C7-1 -> 0.0092467609 | F8: 44441 | G8: 1689.1 | H8: =G8/G7-1 -> 0.0067650127
B9: 44442 | C9: 17323.6 | D9: =C9/C8-1 -> 0.0051902763 | F9: 44442 | G9: 1700.65 | H9: =G9/G8-1 -> 0.006837961
B10: 44445 | C10: 17377.8 | D10: =C10/C9-1 -> 0.00312868 | F10: 44445 | G10: 1730.4 | H10: =G10/G9-1 -> 0.017493311
B11: 44446 | C11: 17362.1 | D11: =C11/C10-1 -> -0.00090345153 | F11: 44446 | G11: 1706.65 | H11: =G11/G10-1 -> -0.01372515
B12: 44447 | C12: 17353.5 | D12: =C12/C11-1 -> -0.00049533179 | F12: 44447 | G12: 1693.25 | H12: =G12/G11-1 -> -0.0078516392
B13: 44448 | C13: 17369.25 | D13: =C13/C12-1 -> 0.00090759789 | F13: 44448 | G13: 1691.6 | H13: =G13/G12-1 -> -0.0009744574
B14: 44452 | C14: 17355.3 | D14: =C14/C13-1 -> -0.00080314349 | F14: 44452 | G14: 1691.9 | H14: =G14/G13-1 -> 0.00017734689
B15: 44453 | C15: 17380 | D15: =C15/C14-1 -> 0.0014231964 | F15: 44453 | G15: 1686.15 | H15: =G15/G14-1 -> -0.003398546
B16: 44454 | C16: 17519.45 | D16: =C16/C15-1 -> 0.0080235903 | F16: 44454 | G16: 1711.45 | H16: =G16/G15-1 -> 0.015004596
B17: 44455 | C17: 17629.5 | D17: =C17/C16-1 -> 0.0062815899 | F17: 44455 | G17: 1702.25 | H17: =G17/G16-1 -> -0.0053755587
B18: 44456 | C18: 17585.15 | D18: =C18/C17-1 -> -0.0025156698 | F18: 44456 | G18: 1691.3 | H18: =G18/G17-1 -> -0.0064326627
... B1245: 46262 | C1245: 24175.65 | D1245: =C1245/C1244-1 -> 0.0035200086 | F1245: 46262 | G1245: 1144 | H1245: =G1245/G1244-1 -> 0.029888369

Sheet DATA>>

Sheet DATA Sheet
A1: COMPANY NAME | B1: INFOSYS LTD | E1: =IF(B2<>B3, "A NEW VERSION OF THE WORKSHEET IS AVAILABLE", "")
A2: LATEST VERSION | B2: 2.1 | E2: PLEASE DO NOT MAKE ANY CHANGES TO THIS SHEET
A3: CURRENT VERSION | B3: 2.1
A5: META
A6: Number of shares | B6: =IF(B9>0, B9/B8, 0) -> 405.80566
A7: Face Value | B7: 5
A8: Current Price | B8: 1144
A9: Market Capitalization | B9: 464241.67
A15: PROFIT & LOSS
A16: Report Date | B16: 42825 | C16: 43190 | D16: 43555 | E16: 43921 | F16: 44286 | G16: 44651 | H16: 45016 | I16: 45382 | J16: 45747 | K16: 46112
A17: Sales | B17: 59289 | C17: 61941 | D17: 73107 | E17: 79047 | F17: 85912 | G17: 103940 | H17: 124014 | I17: 128933 | J17: 136592 | K17: 148819
A18: Raw Material Cost
A19: Change in Inventory
A20: Power and Fuel | B20: 180 | C20: 162 | D20: 171 | E20: 176 | F20: 99 | G20: 93 | H20: 155 | I20: 172 | J20: 196 | K20: 196
A21: Other Mfr. Exp | B21: 7148 | C21: 7688 | D21: 10376 | E21: 11370 | F21: 12682 | G21: 20148 | H21: 25277 | I21: 26505 | J21: 29967 | K21: 32832
A22: Employee Cost | B22: 30953 | C22: 32481 | D22: 38303 | E22: 42442 | F22: 45185 | G22: 51675 | H22: 62779 | I22: 65155 | J22: 67484 | K22: 73257
A23: Selling and admin | B23: 3273 | C23: 3377 | D23: 4256 | E23: 4353 | F23: 2541 | G23: 3464 | H23: 4085 | I23: 4199 | J23: 4734 | K23: 5515
A24: Other Expenses | B24: 528 | C24: 936 | D24: 1327 | E24: 671 | F24: 948 | G24: 732 | H24: 1024 | I24: 1145 | J24: 712 | K24: 1006
A25: Other Income | B25: 3062 | C25: 4019 | D25: 2852 | E25: 2700 | F25: 2467 | G25: 3224 | H25: 3859 | I25: 7417 | J25: 4782 | K25: 5345
A26: Depreciation | B26: 1331 | C26: 1408 | D26: 1599 | E26: 2144 | F26: 2321 | G26: 2429 | H26: 2753 | I26: 2944 | J26: 2619 | K26: 2394
A27: Interest | E27: 114 | F27: 126 | G27: 128 | H27: 157 | I27: 277 | J27: 221 | K27: 207
A28: Profit before tax | B28: 18938 | C28: 19908 | D28: 19927 | E28: 20477 | F28: 24477 | G28: 28495 | H28: 31643 | I28: 35953 | J28: 35441 | K28: 38757
A29: Tax | B29: 5120 | C29: 3753 | D29: 5225 | E29: 4934 | F29: 6429 | G29: 7260 | H29: 8375 | I29: 8719 | J29: 9873 | K29: 9546
A30: Net profit | B30: 13818 | C30: 16155 | D30: 14702 | E30: 15543 | F30: 18048 | G30: 21235 | H30: 23268 | I30: 27234 | J30: 25568 | K30: 29211
A31: Dividend Amount | B31: 5912.2 | C31: 9500.4 | D31: 9365.4 | E31: 7451.5 | F31: 11502 | G31: 13038.6 | H31: 14103.2 | I31: 19090 | J31: 17853.6 | K31: 19459.2
A40: Quarters
A41: Report Date | B41: 45382 | C41: 45473 | D41: 45565 | E41: 45657 | F41: 45747 | G41: 45838 | H41: 45930 | I41: 46022 | J41: 46112 | K41: 46203
A42: Sales | B42: 32001 | C42: 33283 | D42: 34257 | E42: 34915 | F42: 34136 | G42: 35275 | H42: 36907 | I42: 37996 | J42: 38641 | K42: 39957
A43: Expenses | B43: 24286 | C43: 25119 | D43: 25856 | E43: 26361 | F43: 25757 | G43: 26829 | H43: 28059 | I43: 28826 | J43: 29093 | K43: 29996
A44: Other Income | B44: 3483 | C44: 721 | D44: 1737 | E44: 1001 | F44: 1323 | G44: 882 | H44: 2268 | I44: 1131 | J44: 1063 | K44: 874
A45: Depreciation | B45: 722 | C45: 698 | D45: 670 | E45: 661 | F45: 590 | G45: 613 | H45: 595 | I45: 585 | J45: 601 | K45: 613
A46: Interest | B46: 62 | C46: 59 | D46: 61 | E46: 50 | F46: 51 | G46: 55 | H46: 52 | I46: 45 | J46: 54 | K46: 61
A47: Profit before tax | B47: 10414 | C47: 8128 | D47: 9407 | E47: 8844 | F47: 9061 | G47: 8660 | H47: 10469 | I47: 9671 | J47: 9956 | K47: 10161
A48: Tax | B48: 1934 | C48: 2360 | D48: 2594 | E48: 2486 | F48: 2433 | G48: 2546 | H48: 2710 | I48: 2308 | J48: 1981 | K48: 2912
A49: Net profit | B49: 8480 | C49: 5768 | D49: 6813 | E49: 6358 | F49: 6628 | G49: 6114 | H49: 7759 | I49: 7363 | J49: 7975 | K49: 7249
A50: Operating Profit | B50: 7715 | C50: 8164 | D50: 8401 | E50: 8554 | F50: 8379 | G50: 8446 | H50: 8848 | I50: 9170 | J50: 9548 | K50: 9961
A55: BALANCE SHEET
A56: Report Date | B56: 42825 | C56: 43190 | D56: 43555 | E56: 43921 | F56: 44286 | G56: 44651 | H56: 45016 | I56: 45382 | J56: 45747 | K56: 46112
A57: Equity Share Capital | B57: 1148 | C57: 1092 | D57: 2178 | E57: 2129 | F57: 2130 | G57: 2103 | H57: 2074 | I57: 2075 | J57: 2076 | K57: 2027
A58: Reserves | B58: 66869 | C58: 62410 | D58: 60533 | E58: 60105 | F58: 69401 | G58: 67203 | H58: 65671 | I58: 79101 | J58: 85256 | K58: 78847
A59: Borrowings | E59: 3165 | F59: 3854 | G59: 3786 | H59: 4266 | I59: 3766 | J59: 3459 | K59: 3749
A60: Other Liabilities | B60: 11868 | C60: 11870 | D60: 15678 | E60: 15086 | F60: 18043 | G60: 25454 | H60: 28547 | I60: 30008 | J60: 33648 | K60: 41078
A61: Total | B61: 79885 | C61: 75372 | D61: 78389 | E61: 80485 | F61: 93428 | G61: 98546 | H61: 100558 | I61: 114950 | J61: 124439 | K61: 125701
A62: Net Block | B62: 8605 | C62: 9157 | D62: 10497 | E62: 13974 | F62: 14599 | G62: 14938 | H62: 15431 | I62: 14327 | J62: 13359 | K62: 13836
A63: Capital Work in Progress | B63: 1247 | C63: 1442 | D63: 1212 | E63: 945 | F63: 906 | G63: 411 | H63: 275 | I63: 277 | J63: 778 | K63: 512
A64: Investments | B64: 24977 | C64: 17899 | D64: 18139 | E64: 17922 | F64: 24155 | G64: 28336 | H64: 28162 | I64: 34659 | J64: 38518 | K64: 38075
A65: Other Assets | B65: 45056 | C65: 46874 | D65: 48541 | E65: 47644 | F65: 53768 | G65: 54861 | H65: 56690 | I65: 65687 | J65: 71784 | K65: 73278
A66: Total | B66: 79885 | C66: 75372 | D66: 78389 | E66: 80485 | F66: 93428 | G66: 98546 | H66: 100558 | I66: 114950 | J66: 124439 | K66: 125701
A67: Receivables | B67: 10960 | C67: 12151 | D67: 13370 | E67: 15459 | F67: 16394 | G67: 18966 | H67: 20773 | I67: 25152 | J67: 26413 | K67: 30337
A68: Inventory
A69: Cash & Bank | B69: 19153 | C69: 16770 | D69: 15551 | E69: 13562 | F69: 17612 | G69: 12270 | H69: 6534 | I69: 8191 | J69: 14265 | K69: 8727
A70: No. of Equity Shares | B70: 2296944664 | C70: 2184114257 | D70: 4356279444 | E70: 4258992566 | F70: 4260660846 | G70: 4206738641 | H70: 4148560044 | I70: 4150867464 | J70: 4153263455 | K70: 4055591723
A71: New Bonus Shares | D71: 2184191490
A72: Face value | B72: 5 | C72: 5 | D72: 5 | E72: 5 | F72: 5 | G72: 5 | H72: 5 | I72: 5 | J72: 5 | K72: 5
A80: CASH FLOW:
A81: Report Date | B81: 42825 | C81: 43190 | D81: 43555 | E81: 43921 | F81: 44286 | G81: 44651 | H81: 45016 | I81: 45382 | J81: 45747 | K81: 46112
A82: Cash from Operating Activity | B82: 10478 | C82: 12475 | D82: 13989 | E82: 15572 | F82: 19902 | G82: 22096 | H82: 19169 | I82: 20787 | J82: 29409 | K82: 28164
A83: Cash from Investing Activity | B83: -13533 | C83: 5678 | D83: -637 | E83: -170 | F83: -6286 | G83: -3163 | H83: 952 | I83: -3305 | J83: -1956 | K83: 4085
A84: Cash from Financing Activity | B84: -6968 | C84: -20536 | D84: -14571 | E84: -17391 | F84: -9566 | G84: -24275 | H84: -25857 | I84: -15825 | J84: -21379 | K84: -37787
A85: Net Cash Flow | B85: -10023 | C85: -2383 | D85: -1219 | E85: -1989 | F85: 4050 | G85: -5342 | H85: -5736 | I85: 1657 | J85: 6074 | K85: -5538
A90: PRICE: | B90: 511.13 | C90: 565.9 | D90: 743.85 | E90: 641.5 | F90: 1368.05 | G90: 1906.85 | H90: 1427.95 | I90: 1498.05 | J90: 1570.65 | K90: 1250.6
A92: DERIVED:
A93: Adjusted Equity Shares in Cr | B93: 459.39 | C93: 436.82 | D93: 436.89 | E93: 425.9 | F93: 426.07 | G93: 420.67 | H93: 414.86 | I93: 415.09 | J93: 415.33 | K93: 405.56

Sheet Balance sheet
C3: 42064 | D3: 42430 | E3: 42795 | F3: 43160 | G3: 43525 | H3: 43891 | I3: 44256 | J3: 44621 | K3: 44986 | L3: 45352 | M3: 45717 | N3: 46082
B4: Equity Capital | C4: 574 | D4: 1148 | E4: 1148 | F4: 1092 | G4: 2178 | H4: 2129 | I4: 2130 | J4: 2103 | K4: 2074 | L4: 2075 | M4: 2076 | N4: 2027
B5: Reserves | C5: 47494 | D5: 59934 | E5: 66869 | F5: 62410 | G5: 60533 | H5: 60105 | I5: 69401 | J5: 67203 | K5: 65671 | L5: 79101 | M5: 85256 | N5: 78847
B6: Borrowings + | C6: 0 | D6: 0 | E6: 0 | F6: 0 | G6: 0 | H6: 3165 | I6: 3854 | J6: 3786 | K6: 4266 | L6: 3766 | M6: 3459 | N6: 3749
B7: Other Liabilities + | C7: 13745 | D7: 11650 | E7: 11868 | F7: 11870 | G7: 15678 | H7: 15086 | I7: 18043 | J7: 25454 | K7: 28547 | L7: 30008 | M7: 33648 | N7: 41078
B8: Total Liabilities | C8: 61813 | D8: 72732 | E8: 79885 | F8: 75372 | G8: 78389 | H8: 80485 | I8: 93428 | J8: 98546 | K8: 100558 | L8: 114950 | M8: 124439 | N8: 125701
B9: Fixed Assets + | C9: 7347 | D9: 8248 | E9: 8605 | F9: 9157 | G9: 10497 | H9: 13974 | I9: 14599 | J9: 14938 | K9: 15431 | L9: 14327 | M9: 13359 | N9: 13836
B10: CWIP | C10: 769 | D10: 934 | E10: 1247 | F10: 1442 | G10: 1212 | H10: 945 | I10: 906 | J10: 411 | K10: 275 | L10: 277 | M10: 778 | N10: 512
B11: Investments | C11: 6857 | D11: 11078 | E11: 24977 | F11: 17899 | G11: 18139 | H11: 17922 | I11: 24155 | J11: 28336 | K11: 28162 | L11: 34659 | M11: 38518 | N11: 38075
B12: Other Assets - | C12: 46840 | D12: 52472 | E12: 45056 | F12: 46874 | G12: 48541 | H12: 47644 | I12: 53768 | J12: 54861 | K12: 56690 | L12: 65687 | M12: 71784 | N12: 73278
B13: Trade receivables | C13: 8627 | D13: 9798 | E13: 10960 | F13: 12151 | G13: 13370 | H13: 15459 | I13: 16394 | J13: 18966 | K13: 20773 | L13: 25152 | M13: 26413 | N13: 30337
B14: Cash Equivalents | C14: 27722 | D14: 29176 | E14: 19153 | F14: 16770 | G14: 15551 | H14: 13562 | I14: 17612 | J14: 12270 | K14: 6534 | L14: 8191 | M14: 14265 | N14: 8727
B15: Loans n Advances | C15: 332 | D15: 531 | E15: 715 | F15: 760 | G15: 1304 | H15: 1069 | I15: 1138 | J15: 1576 | K15: 2124 | L15: 8748 | M15: 5532 | N15: 5571
... B19: Trade payable | C19: 124 | D19: 623 | E19: 269 | F19: 738 | G19: 1604 | H19: 1529 | I19: 1562 | J19: 2669 | K19: 2426 | L19: 2493 | M19: 2728 | N19: 3539

Sheet CF
C3: 42064 | D3: 42430 | E3: 42795 | F3: 43160 | G3: 43525 | H3: 43891 | I3: 44256 | J3: 44621 | K3: 44986 | L3: 45352 | M3: 45717 | N3: 46082
B4: Cash from Operating Activity - | C4: 7955 | D4: 9578 | E4: 10478 | F4: 12475 | G4: 13989 | H4: 15572 | I4: 19902 | J4: 22096 | K4: 19169 | L4: 20787 | M4: 29409 | N4: 28164
B5: Profit from operations | C5: 15028 | D5: 16425 | E5: 17938 | F5: 18797 | G5: 20577 | H5: 21355 | I5: 25782 | J5: 29083 | K5: 32207 | L5: 33650 | M5: 35181 | N5: 38082
B6: Receivables | C6: -1433 | D6: -1373 | E6: -1825 | F6: -1579 | G6: -2268 | H6: -3621 | I6: -1414 | J6: -5725 | K6: -5065 | L6: -2933 | M6: -2994 | N6: -6018
B7: Payables | C7: 0 | D7: 499 | E7: -354 | F7: 466 | G7: 866 | H7: -75 | I7: -5 | J7: 1112 | K7: -243 | L7: 67 | M7: 236 | N7: 812
B8: Loans Advances | C8: -326 | D8: 0 | E8: 0 | F8: 0 | G8: 0 | H8: 0 | I8: -684 | J8: -1125 | K8: -2171 | L8: -1645 | M8: -1942 | N8: -3870
B9: Other WC items | C9: 1175 | D9: -623 | E9: -248 | F9: 845 | G9: 1085 | H9: 1794 | I9: 2284 | J9: 5487 | K9: 2248 | L9: -117 | M9: 3529 | N9: 6330
B10: Working capital changes | C10: -584 | D10: -1497 | E10: -2427 | F10: -268 | G10: -317 | H10: -1902 | I10: 181 | J10: -251 | K10: -5231 | L10: -4628 | M10: -1171 | N10: -2746
B11: Direct taxes | C11: -6489 | D11: -5350 | E11: -5033 | F11: -6054 | G11: -6271 | H11: -3881 | I11: -6061 | J11: -6736 | K11: -7807 | L11: -8235 | M11: -4601 | N11: -7172
B12: Cash from Investing Activity - | C12: 628 | D12: -1216 | E12: -13533 | F12: 5678 | G12: -637 | H12: -170 | I12: -6286 | J12: -3163 | K12: 952 | L12: -3305 | M12: -1956 | N12: 4085
B13: Fixed assets purchased | C13: -1986 | D13: -2308 | E13: -2292 | F13: -1842 | G13: -2306 | H13: -3063 | I13: -1720 | J13: -1787 | K13: -2130 | L13: -1832 | M13: -1587 | N13: -2170
B14: Investments purchased | C14: -23184 | D14: -23180 | E14: -53667 | F14: -57555 | G14: -74347 | H14: -32846 | I14: -42876 | J14: -53055 | K14: -67225 | L14: -68539 | M14: -76144 | N14: -73086
B15: Investments sold | C15: 24406 | D15: 23545 | E15: 47917 | F15: 59823 | G15: 72846 | H15: 34591 | I15: 37340 | J15: 52180 | K15: 68505 | L15: 62729 | M15: 77550 | N15: 79455
... B29: Net Cash Flow | C29: 3622 | D29: 1454 | E29: -10023 | F29: -2383 | G29: -1219 | H29: -1989 | I29: 4050 | J29: -5342 | K29: -5736 | L29: 1657 | M29: 6074 | N29: -5538

Sheet P&L
C3: 42064 | D3: 42430 | E3: 42795 | F3: 43160 | G3: 43525 | H3: 43891 | I3: 44256 | J3: 44621 | K3: 44986 | L3: 45352 | M3: 45717 | N3: 46082 | O3: TTM
B4: Sales + | C4: 47300 | D4: 53983 | E4: 59289 | F4: 61941 | G4: 73107 | H4: 79047 | I4: 85912 | J4: 103940 | K4: 124014 | L4: 128933 | M4: 136592 | N4: 148819 | O4: 153501
B5: Expenses + | C5: 33330 | D5: 38274 | E5: 42082 | F5: 44644 | G5: 54433 | H5: 59012 | I5: 61455 | J5: 76112 | K5: 93320 | L5: 97176 | M5: 103093 | N5: 112806 | O5: 115974
B6: Operating Profit | C6: 13970 | D6: 15709 | E6: 17207 | F6: 17297 | G6: 18674 | H6: 20035 | I6: 24457 | J6: 27828 | K6: 30694 | L6: 31757 | M6: 33499 | N6: 36013 | O6: 37527
B7: OPM % | C7: 0.3 | D7: 0.29 | E7: 0.29 | F7: 0.28 | G7: 0.26 | H7: 0.25 | I7: 0.28 | J7: 0.27 | K7: 0.25 | L7: 0.25 | M7: 0.25 | N7: 0.24 | O7: 0.24
B8: Other Income + | C8: 3749 | D8: 3006 | E8: 3062 | F8: 4019 | G8: 2852 | H8: 2700 | I8: 2467 | J8: 3224 | K8: 3859 | L8: 7417 | M8: 4782 | N8: 5345 | O8: 5336
B9: Interest | C9: 8 | D9: 0 | E9: 0 | F9: 0 | G9: 0 | H9: 114 | I9: 126 | J9: 128 | K9: 157 | L9: 277 | M9: 221 | N9: 207 | O9: 212
B10: Depreciation | C10: 913 | D10: 1115 | E10: 1331 | F10: 1408 | G10: 1599 | H10: 2144 | I10: 2321 | J10: 2429 | K10: 2753 | L10: 2944 | M10: 2619 | N10: 2394 | O10: 2394
B11: Profit before tax | C11: 16798 | D11: 17600 | E11: 18938 | F11: 19908 | G11: 19927 | H11: 20477 | I11: 24477 | J11: 28495 | K11: 31643 | L11: 35953 | M11: 35441 | N11: 38757 | O11: 40257
B12: Tax % | C12: 0.28 | D12: 0.28 | E12: 0.27 | F12: 0.19 | G12: 0.26 | H12: 0.24 | I12: 0.26 | J12: 0.25 | K12: 0.26 | L12: 0.24 | M12: 0.28 | N12: 0.25
B13: Net Profit + | C13: 12164 | D13: 12693 | E13: 13818 | F13: 16155 | G13: 14702 | H13: 15543 | I13: 18048 | J13: 21235 | K13: 23268 | L13: 27234 | M13: 25568 | N13: 29211 | O13: 30346
D16: =0.1213*D5 -> 4642.6362
D17: =0.0651*D5 -> 2491.6374
D18: =SUM(D16:D17) -> 7134.2736

Sheet KPI
C3: Metric | D3: 42064 | E3: 42430 | F3: 42795 | G3: 43160 | H3: 43525 | I3: 43891 | J3: 44256 | K3: 44621 | L3: 44986 | M3: 45352 | N3: 45717 | O3: 46082
C4: Active Clients | D4: 950 | E4: 1092 | F4: 1162 | G4: 1204 | H4: 1279 | I4: 1411 | J4: 1626 | K4: 1741 | L4: 1872 | M4: 1882 | N4: 1869 | O4: 1965
C5: Mega Clients ($100M+ revenue) | E5: 14 | F5: 19 | G5: 20 | H5: 25 | I5: 28 | J5: 32 | K5: 38 | L5: 40 | M5: 40 | N5: 42 | O5: 45
C6: Total Headcount | E6: 194044 | F6: 200364 | G6: 204107 | H6: 228123 | I6: 242371 | J6: 259619 | K6: 314015 | L6: 343234 | M6: 317240 | N6: 323578 | O6: 328594
C7: Large Deal Total Contract Value (TCV)(USD Bn) | E7: 2.8 | F7: 3.5 | H7: 6.3 | I7: 9 | J7: 14 | K7: 9.5 | L7: 9.8 | M7: 17.7 | N7: 11.6 | O7: 14.9
C8: Voluntary Attrition (LTM, IT Services)% | E8: 13.6 | F8: 15 | G8: 16.4 | I8: 17.4 | J8: 10.9 | K8: 27.7 | L8: 20.9 | M8: 12.6 | N8: 14.1 | O8: 12.6
C9: Large Clients ($50M+ revenue) | F9: 56 | G9: 57 | H9: 60 | L9: 75 | M9: 83 | N9: 85 | O9: 88
C10: Freshers Hired | J10: 19000 | K10: 60405 | L10: 50000 | M10: 11900 | N10: 15288 | O10: 20000
C11: Utilization (Excluding Trainees) % | E11: 80.8 | F11: 81.7 | G11: 84.6 | H11: 84.3 | I11: 84 | O11: 84.4
C12: Onsite Mix | F12: 53.7 | G12: 55.4 | H12: 54.9 | I12: 54.8
C13: R&D Expenditure (Percentage of Turnover) | D13: 1.3 | E13: 0.8 | F13: 0.6 | G13: 0.6 | H13: 0.6 | I13: 0.6 | J13: 0.6 | K13: 0.5 | L13: 0.5 | M13: 0.54 | N13: 0.62
